Workbook

Sheet HiringCafe_Database
A1: Posted Time | B1: Role | C1: Area | D1: Work Type | E1: Contract Type | F1: Company | G1: Company & Description | H1: Requirements Summary | I1: Technical Tools mentioned | J1: Job Posting | K1: Added Date | L1: Type of Search | M1: Posted Date (DATE format)
A2: 12h | B2: Insight Analyst - Customer Success | C2: Budapest, Budapest, Hungary | D2: Hybrid | E2: Full Time | F2: NielsenIQ | G2: NielsenIQNYSE: NIQ: Provides data and analytics on global consumer buying behavior. | H2: 1+ YOE1-3 years of data analysis experience; English fluency; ability to collaborate with clients; knowledge of data delivery and reporting. | I2: Not available | J2: Job Posting | K2: 46083 | L2: Departments - Data and Analytics, Budapest (Remote, Hybrid, Onsite), No keyword search, 6 months | M2: =IFERROR(__xludf.DUMMYFUNCTION("TEXT( IF(RIGHT(A2,2)=""mo"", EDATE(DATEVALUE(K2), -VALUE(REGEXEXTRACT(A2,""\d+""))), DATEVALUE(K2) - IF(RIGHT(A2,1)=""h"", VALUE(REGEXEXTRACT(A2,""\d+""))/24, IF(RIGHT(A2,1)=""d"", VALUE(REGEXEXTRACT(A2,""\d+"")), IF(RIGHT(A2,1"&")=""w"", VALUE(REGEXEXTRACT(A2,""\d+""))*7, 0))) ) , ""YYYY-M-D"")"),"2026-3-1") -> 2026-3-1
A3: 1d | B3: Senior SEO/GEO Consultant | C3: Budapest, Budapest, Hungary | D3: Hybrid | E3: Full Time | F3: DEPT | G3: DEPT: Global digital agency providing integrated technology and marketing services. | H3: 5+ YOE5+ years in SEO; fluent English; strategic, analytical thinker; strong communication; able to work independently in a hybrid setting. | I3: Not available | J3: Job Posting | K3: 46083 | L3: Departments - Data and Analytics, Budapest (Remote, Hybrid, Onsite), No keyword search, 6 months | M3: =IFERROR(__xludf.DUMMYFUNCTION("TEXT( IF(RIGHT(A3,2)=""mo"", EDATE(DATEVALUE(K3), -VALUE(REGEXEXTRACT(A3,""\d+""))), DATEVALUE(K3) - IF(RIGHT(A3,1)=""h"", VALUE(REGEXEXTRACT(A3,""\d+""))/24, IF(RIGHT(A3,1)=""d"", VALUE(REGEXEXTRACT(A3,""\d+"")), IF(RIGHT(A3,1"&")=""w"", VALUE(REGEXEXTRACT(A3,""\d+""))*7, 0))) ) , ""YYYY-M-D"")"),"2026-3-1") -> 2026-3-1
A4: 2d | B4: Global Master Data Administrator Intern (Budapest, HU, H-1138) | C4: Budapest, Budapest, Hungary | D4: Hybrid | E4: All Commitments Available | F4: Givaudan | G4: GivaudanSIX Swiss Exchange: GIVN: Global manufacturer of flavors, fragrances, and active cosmetic ingredients. | H4: Pursuing university degree (IT or Business); fluent English; intermediate Excel; SAP experience beneficial. | I4: Microsoft Excel, SAP | J4: Job Posting | K4: 46083 | L4: Departments - Data and Analytics, Budapest (Remote, Hybrid, Onsite), No keyword search, 6 months | M4: =IFERROR(__xludf.DUMMYFUNCTION("TEXT( IF(RIGHT(A4,2)=""mo"", EDATE(DATEVALUE(K4), -VALUE(REGEXEXTRACT(A4,""\d+""))), DATEVALUE(K4) - IF(RIGHT(A4,1)=""h"", VALUE(REGEXEXTRACT(A4,""\d+""))/24, IF(RIGHT(A4,1)=""d"", VALUE(REGEXEXTRACT(A4,""\d+"")), IF(RIGHT(A4,1"&")=""w"", VALUE(REGEXEXTRACT(A4,""\d+""))*7, 0))) ) , ""YYYY-M-D"")"),"2026-2-28") -> 2026-2-28
A5: 2d | B5: Head of Experimentations | C5: Ukraine or Turkey or Serbia or Georgia or Moldova or Montenegro or Macedonia or Kazakhstan or Europe | D5: Remote | E5: Full Time | F5: Ruby Labs | G5: Ruby Labs: Creates and operates innovative consumer mobile products globally. | H5: 7+ YOESenior growth leader with 7+ years in growth, CRO, product growth, or performance strategy; proven success scaling digital subscription products; strong analytics and experimentation expertise; English proficiency. | I5: A/B testing platforms, Analytics platforms | J5: Job Posting | K5: 46083 | L5: Departments - Data and Analytics, Budapest (Remote, Hybrid, Onsite), No keyword search, 6 months | M5: =IFERROR(__xludf.DUMMYFUNCTION("TEXT( IF(RIGHT(A5,2)=""mo"", EDATE(DATEVALUE(K5), -VALUE(REGEXEXTRACT(A5,""\d+""))), DATEVALUE(K5) - IF(RIGHT(A5,1)=""h"", VALUE(REGEXEXTRACT(A5,""\d+""))/24, IF(RIGHT(A5,1)=""d"", VALUE(REGEXEXTRACT(A5,""\d+"")), IF(RIGHT(A5,1"&")=""w"", VALUE(REGEXEXTRACT(A5,""\d+""))*7, 0))) ) , ""YYYY-M-D"")"),"2026-2-28") -> 2026-2-28
A6: 3d | B6: Quantitative Researcher | C6: Budapest, Budapest, Hungary | D6: Onsite | E6: Full Time | F6: MSCI | G6: MSCINYSE: MSCI: Provides investment indices, data, and portfolio risk analytics. | H6: Advanced degree (Masters or PhD) in a quantitative field; strong quantitative and problem-solving skills; ability to communicate with senior stakeholders; interest in empirical modeling and data science; Proficiency in Python, MATLAB, and production C++. | I6: Python, MATLAB, C++ | J6: Job Posting | K6: 46083 | L6: Departments - Data and Analytics, Budapest (Remote, Hybrid, Onsite), No keyword search, 6 months | M6: =IFERROR(__xludf.DUMMYFUNCTION("TEXT( IF(RIGHT(A6,2)=""mo"", EDATE(DATEVALUE(K6), -VALUE(REGEXEXTRACT(A6,""\d+""))), DATEVALUE(K6) - IF(RIGHT(A6,1)=""h"", VALUE(REGEXEXTRACT(A6,""\d+""))/24, IF(RIGHT(A6,1)=""d"", VALUE(REGEXEXTRACT(A6,""\d+"")), IF(RIGHT(A6,1"&")=""w"", VALUE(REGEXEXTRACT(A6,""\d+""))*7, 0))) ) , ""YYYY-M-D"")"),"2026-2-27") -> 2026-2-27
A7: 3d | B7: Digitalization Specialist, Reporting CoE (Budapest, PE, HU, 1062) | C7: Budapest, Budapest, Hungary | D7: Hybrid | E7: Full Time | F7: Grundfos | G7: Grundfos: Global manufacturer of energy-efficient water pumps and systems. | H7: 3+ YOEBachelor’s or Master’s in Finance, Economics, Business, Data/Analytics; 3–5 years in finance processes; hands-on with Power BI, Power Automate, Power Apps; familiarity with Copilot Studio and agentic AI workflows. | I7: Power BI, Power Automate, Power Apps, Microsoft Copilot Studio, Agentic AI workflows | J7: Job Posting | K7: 46083 | L7: Departments - Data and Analytics, Budapest (Remote, Hybrid, Onsite), No keyword search, 6 months | M7: =IFERROR(__xludf.DUMMYFUNCTION("TEXT( IF(RIGHT(A7,2)=""mo"", EDATE(DATEVALUE(K7), -VALUE(REGEXEXTRACT(A7,""\d+""))), DATEVALUE(K7) - IF(RIGHT(A7,1)=""h"", VALUE(REGEXEXTRACT(A7,""\d+""))/24, IF(RIGHT(A7,1)=""d"", VALUE(REGEXEXTRACT(A7,""\d+"")), IF(RIGHT(A7,1"&")=""w"", VALUE(REGEXEXTRACT(A7,""\d+""))*7, 0))) ) , ""YYYY-M-D"")"),"2026-2-27") -> 2026-2-27
A8: 3d | B8: Data analyst (Budapest, BU, HU, 1068) | C8: Budapest, Budapest, Hungary | D8: Onsite | E8: Full Time | F8: Bertelsmann | G8: Bertelsmann: Global media, publishing, and business services conglomerate. | H8: 2+ YOE2-4 years of data analyst or business analyst experience; strong SQL; Python; Power BI; advanced Excel; statistical basics and data modeling; data visualization; stakeholder management. | I8: SQL, Python, Power BI, Excel, Power Pivot, Power Query | J8: Job Posting | K8: 46083 | L8: Departments - Data and Analytics, Budapest (Remote, Hybrid, Onsite), No keyword search, 6 months | M8: =IFERROR(__xludf.DUMMYFUNCTION("TEXT( IF(RIGHT(A8,2)=""mo"", EDATE(DATEVALUE(K8), -VALUE(REGEXEXTRACT(A8,""\d+""))), DATEVALUE(K8) - IF(RIGHT(A8,1)=""h"", VALUE(REGEXEXTRACT(A8,""\d+""))/24, IF(RIGHT(A8,1)=""d"", VALUE(REGEXEXTRACT(A8,""\d+"")), IF(RIGHT(A8,1"&")=""w"", VALUE(REGEXEXTRACT(A8,""\d+""))*7, 0))) ) , ""YYYY-M-D"")"),"2026-2-27") -> 2026-2-27
A9: 4d | B9: Data Platform Developer Trainee | C9: Budapest, Budapest, Hungary | D9: Remote | E9: Internship | F9: Hiflylabs | G9: Hiflylabs: We provide expert data engineering, AI, and analytics solutions. | H9: 0+ YOECurious, eager to learn data engineering, with SQL basics and Python familiarity; active student, at least 1 full semester remaining, 20 hours/week. | I9: SQL, Python, Git | J9: Job Posting | K9: 46083 | L9: Departments - Data and Analytics, Budapest (Remote, Hybrid, Onsite), No keyword search, 6 months | M9: =IFERROR(__xludf.DUMMYFUNCTION("TEXT( IF(RIGHT(A9,2)=""mo"", EDATE(DATEVALUE(K9), -VALUE(REGEXEXTRACT(A9,""\d+""))), DATEVALUE(K9) - IF(RIGHT(A9,1)=""h"", VALUE(REGEXEXTRACT(A9,""\d+""))/24, IF(RIGHT(A9,1)=""d"", VALUE(REGEXEXTRACT(A9,""\d+"")), IF(RIGHT(A9,1"&")=""w"", VALUE(REGEXEXTRACT(A9,""\d+""))*7, 0))) ) , ""YYYY-M-D"")"),"2026-2-26") -> 2026-2-26
A10: 4d | B10: Jr. Master Data Specialist_fixed-term (Budapest, Budapest, HU, 1007) | C10: Budapest, Budapest, Hungary | D10: Onsite | E10: Contract | F10: Reckitt | G10: ReckittLondon Stock Exchange: RKT: Manufacturing and selling consumer hygiene, health, and nutrition products. | H10: 1+ YOEBachelor’s degree in business; at least 1 year data or project management experience; fluent in Hungarian and English; strong Excel skills; experience with integrated finance data handling; good communication and analytical skills; high precision. | I10: Excel, SAP, JDE | J10: Job Posting | K10: 46083 | L10: Departments - Data and Analytics, Budapest (Remote, Hybrid, Onsite), No keyword search, 6 months | M10: =IFERROR(__xludf.DUMMYFUNCTION("TEXT( IF(RIGHT(A10,2)=""mo"", EDATE(DATEVALUE(K10), -VALUE(REGEXEXTRACT(A10,""\d+""))), DATEVALUE(K10) - IF(RIGHT(A10,1)=""h"", VALUE(REGEXEXTRACT(A10,""\d+""))/24, IF(RIGHT(A10,1)=""d"", VALUE(REGEXEXTRACT(A10,""\d+"")), IF(RI"&"GHT(A10,1)=""w"", VALUE(REGEXEXTRACT(A10,""\d+""))*7, 0))) ) , ""YYYY-M-D"")"),"2026-2-26") -> 2026-2-26
A11: 4d | B11: AI Model Validation Expert | C11: Budapest, Budapest, Hungary | D11: Hybrid | E11: Full Time | F11: PwC | G11: PwC: Global provider of audit, tax, and professional consulting services. | H11: 3+ YOE3+ years in developing/validating AI models; degree in quantitative fields; experience in AI/ML, risk, governance; strong communication and leadership; English fluency; German a plus. | I11: Not available | J11: Job Posting | K11: 46083 | L11: Departments - Data and Analytics, Budapest (Remote, Hybrid, Onsite), No keyword search, 6 months | M11: =IFERROR(__xludf.DUMMYFUNCTION("TEXT( IF(RIGHT(A11,2)=""mo"", EDATE(DATEVALUE(K11), -VALUE(REGEXEXTRACT(A11,""\d+""))), DATEVALUE(K11) - IF(RIGHT(A11,1)=""h"", VALUE(REGEXEXTRACT(A11,""\d+""))/24, IF(RIGHT(A11,1)=""d"", VALUE(REGEXEXTRACT(A11,""\d+"")), IF(RI"&"GHT(A11,1)=""w"", VALUE(REGEXEXTRACT(A11,""\d+""))*7, 0))) ) , ""YYYY-M-D"")"),"2026-2-26") -> 2026-2-26
A12: 4d | B12: Marketing Analytics Specialist | C12: Budapest, Budapest, Hungary | D12: Onsite | E12: Full Time | F12: Iron Mountain | G12: Iron MountainNYSE: IRM: Provides enterprise information management, storage, and data center services. | H12: Experience in marketing analytics; strong SQL, BigQuery, Python/R; dashboarding with Tableau/Looker Studio; ability to translate data into business insights. | I12: SQL, BigQuery, Google Cloud Platform, Python, R, JavaScript, GA4, GTM, Tableau, Looker Studio | J12: Job Posting | K12: 46083 | L12: Departments - Data and Analytics, Budapest (Remote, Hybrid, Onsite), No keyword search, 6 months | M12: =IFERROR(__xludf.DUMMYFUNCTION("TEXT( IF(RIGHT(A12,2)=""mo"", EDATE(DATEVALUE(K12), -VALUE(REGEXEXTRACT(A12,""\d+""))), DATEVALUE(K12) - IF(RIGHT(A12,1)=""h"", VALUE(REGEXEXTRACT(A12,""\d+""))/24, IF(RIGHT(A12,1)=""d"", VALUE(REGEXEXTRACT(A12,""\d+"")), IF(RI"&"GHT(A12,1)=""w"", VALUE(REGEXEXTRACT(A12,""\d+""))*7, 0))) ) , ""YYYY-M-D"")"),"2026-2-26") -> 2026-2-26
A13: 4d | B13: Process & Data Analyst | C13: Budapest, Budapest, Hungary | D13: Hybrid | E13: Full Time | F13: bp | G13: bpLondon Stock Exchange: BP: Produces and distributes oil, gas, and renewable energy globally. | H13: BA or master’s in economics or related field; demonstrable data analysis/process improvement experience; strong communication; data integration/ETL; data management; governance familiarity; energy sector knowledge. | I13: SQL, Python, ETL, BPMN, UML, Data Visualization, Data Management, Data Sourcing | J13: Job Posting | K13: 46083 | L13: Departments - Data and Analytics, Budapest (Remote, Hybrid, Onsite), No keyword search, 6 months | M13: =IFERROR(__xludf.DUMMYFUNCTION("TEXT( IF(RIGHT(A13,2)=""mo"", EDATE(DATEVALUE(K13), -VALUE(REGEXEXTRACT(A13,""\d+""))), DATEVALUE(K13) - IF(RIGHT(A13,1)=""h"", VALUE(REGEXEXTRACT(A13,""\d+""))/24, IF(RIGHT(A13,1)=""d"", VALUE(REGEXEXTRACT(A13,""\d+"")), IF(RI"&"GHT(A13,1)=""w"", VALUE(REGEXEXTRACT(A13,""\d+""))*7, 0))) ) , ""YYYY-M-D"")"),"2026-2-26") -> 2026-2-26
A14: 4d | B14: Process & Data Analyst | C14: Budapest, Budapest, Hungary | D14: Hybrid | E14: Full Time | F14: bp | G14: bpLondon Stock Exchange: BP: Global energy providing oil, gas, and low-carbon solutions. | H14: BA or master’s in economics or similar; experience in data analysis or process improvement; strong commercial acumen; proficient in data integration, cleansing, transformation, and visualization; good communication skills; knowledge of data governance and security. | I14: SQL, Python, ETL, Data Visualization, BPMN, UML | J14: Job Posting | K14: 46083 | L14: Departments - Data and Analytics, Budapest (Remote, Hybrid, Onsite), No keyword search, 6 months | M14: =IFERROR(__xludf.DUMMYFUNCTION("TEXT( IF(RIGHT(A14,2)=""mo"", EDATE(DATEVALUE(K14), -VALUE(REGEXEXTRACT(A14,""\d+""))), DATEVALUE(K14) - IF(RIGHT(A14,1)=""h"", VALUE(REGEXEXTRACT(A14,""\d+""))/24, IF(RIGHT(A14,1)=""d"", VALUE(REGEXEXTRACT(A14,""\d+"")), IF(RI"&"GHT(A14,1)=""w"", VALUE(REGEXEXTRACT(A14,""\d+""))*7, 0))) ) , ""YYYY-M-D"")"),"2026-2-26") -> 2026-2-26
A15: 4d | B15: Staff Analytics Product Manager – Operations, Strategy & CTO | C15: Bengaluru or Monterrey or Budapest | D15: Hybrid | E15: Full Time | F15: GE Vernova | G15: GE VernovaNYSE: GEV: Global energy manufacturing power generation and grid technologies. | H15: 7+ YOE7+ years in data management, BI, or analytics; Bachelor’s in STEM; AI/ML experience; BI/tools proficiency. | I15: Power BI, Tableau, Databricks, Azure, AWS, Google Cloud | J15: Job Posting | K15: 46083 | L15: Departments - Data and Analytics, Budapest (Remote, Hybrid, Onsite), No keyword search, 6 months | M15: =IFERROR(__xludf.DUMMYFUNCTION("TEXT( IF(RIGHT(A15,2)=""mo"", EDATE(DATEVALUE(K15), -VALUE(REGEXEXTRACT(A15,""\d+""))), DATEVALUE(K15) - IF(RIGHT(A15,1)=""h"", VALUE(REGEXEXTRACT(A15,""\d+""))/24, IF(RIGHT(A15,1)=""d"", VALUE(REGEXEXTRACT(A15,""\d+"")), IF(RI"&"GHT(A15,1)=""w"", VALUE(REGEXEXTRACT(A15,""\d+""))*7, 0))) ) , ""YYYY-M-D"")"),"2026-2-26") -> 2026-2-26
A16: 4d | B16: HR Data & Analytics Expert (Budapest, HU, 1031) | C16: Budapest, Budapest, Hungary | D16: Onsite | E16: Full Time | F16: Graphisoft | G16: Graphisoft: Develops BIM software solutions for architecture and engineering professionals. | H16: 3+ YOEAnalyze HR data, build dashboards, apply AI, and govern HR data to enable strategic HR decisions. | I16: Power BI, Tableau, HRIS, Statistical software | J16: Job Posting | K16: 46083 | L16: Departments - Data and Analytics, Budapest (Remote, Hybrid, Onsite), No keyword search, 6 months | M16: =IFERROR(__xludf.DUMMYFUNCTION("TEXT( IF(RIGHT(A16,2)=""mo"", EDATE(DATEVALUE(K16), -VALUE(REGEXEXTRACT(A16,""\d+""))), DATEVALUE(K16) - IF(RIGHT(A16,1)=""h"", VALUE(REGEXEXTRACT(A16,""\d+""))/24, IF(RIGHT(A16,1)=""d"", VALUE(REGEXEXTRACT(A16,""\d+"")), IF(RI"&"GHT(A16,1)=""w"", VALUE(REGEXEXTRACT(A16,""\d+""))*7, 0))) ) , ""YYYY-M-D"")"),"2026-2-26") -> 2026-2-26
A17: 4d | B17: Workforce Management Analyst | C17: Budapest, Budapest, Hungary | D17: Hybrid | E17: Full Time | F17: Delivery Hero | G17: Delivery HeroFrankfurt Stock Exchange: DHER: Global platform for online food ordering and delivery services. | H17: 3+ YOE3–4 years in workforce management planning/scheduling; English proficiency; advanced Excel; SQL; Python; strong data analysis skills. | I17: Google Suite, Microsoft Office, Excel, SQL, Python, Erlang-C | J17: Job Posting | K17: 46083 | L17: Departments - Data and Analytics, Budapest (Remote, Hybrid, Onsite), No keyword search, 6 months | M17: =IFERROR(__xludf.DUMMYFUNCTION("TEXT( IF(RIGHT(A17,2)=""mo"", EDATE(DATEVALUE(K17), -VALUE(REGEXEXTRACT(A17,""\d+""))), DATEVALUE(K17) - IF(RIGHT(A17,1)=""h"", VALUE(REGEXEXTRACT(A17,""\d+""))/24, IF(RIGHT(A17,1)=""d"", VALUE(REGEXEXTRACT(A17,""\d+"")), IF(RI"&"GHT(A17,1)=""w"", VALUE(REGEXEXTRACT(A17,""\d+""))*7, 0))) ) , ""YYYY-M-D"")"),"2026-2-26") -> 2026-2-26
A18: 4d | B18: Data Scientist (REF5099W) | C18: Budapest or Debrecen or Pécs or Szeged | D18: Hybrid | E18: Full Time | F18: Deutsche Telekom IT Solutions | G18: Deutsche Telekom IT SolutionsFrankfurt Stock Exchange: DTE: Provides integrated IT and telecommunications services to corporate clients. | H18: Bachelor’s degree in IT/related fields; data science/ML/analytics experience; NoSQL; REST/JSON; Python; GitLab CI/CD; Docker/Kubernetes; Elastic/OpenSearch; Kafka; Linux; English. | I18: NoSQL, REST-API, JSON, Python, GitLab CI/CD, Docker, Kubernetes, Elasticsearch/OpenSearch, Kafka, Linux | J18: Job Posting | K18: 46083 | L18: Departments - Data and Analytics, Budapest (Remote, Hybrid, Onsite), No keyword search, 6 months | M18: =IFERROR(__xludf.DUMMYFUNCTION("TEXT( IF(RIGHT(A18,2)=""mo"", EDATE(DATEVALUE(K18), -VALUE(REGEXEXTRACT(A18,""\d+""))), DATEVALUE(K18) - IF(RIGHT(A18,1)=""h"", VALUE(REGEXEXTRACT(A18,""\d+""))/24, IF(RIGHT(A18,1)=""d"", VALUE(REGEXEXTRACT(A18,""\d+"")), IF(RI"&"GHT(A18,1)=""w"", VALUE(REGEXEXTRACT(A18,""\d+""))*7, 0))) ) , ""YYYY-M-D"")"),"2026-2-26") -> 2026-2-26
A19: 4d | B19: Product Analyst, Donor Portal | C19: Georgia or Europe | D19: Remote | E19: Full Time | F19: Fundraise Up | G19: Fundraise Up: AI-powered fundraising platform for nonprofit organizations. | H19: 5+ YOE5+ years as Data/Product Analyst; strong statistics; advanced SQL; Python (NumPy, Pandas, Matplotlib, Scikit-learn); BI tools (Tableau, Power BI, Metabase); strong English; proactive, detail-oriented. | I19: Python, SQL, Tableau, Power BI, Metabase, Grafana, Airflow, Git, ClickHouse, MongoDB, PostgreSQL | J19: Job Posting | K19: 46083 | L19: Departments - Data and Analytics, Budapest (Remote, Hybrid, Onsite), No keyword search, 6 months | M19: =IFERROR(__xludf.DUMMYFUNCTION("TEXT( IF(RIGHT(A19,2)=""mo"", EDATE(DATEVALUE(K19), -VALUE(REGEXEXTRACT(A19,""\d+""))), DATEVALUE(K19) - IF(RIGHT(A19,1)=""h"", VALUE(REGEXEXTRACT(A19,""\d+""))/24, IF(RIGHT(A19,1)=""d"", VALUE(REGEXEXTRACT(A19,""\d+"")), IF(RI"&"GHT(A19,1)=""w"", VALUE(REGEXEXTRACT(A19,""\d+""))*7, 0))) ) , ""YYYY-M-D"")"),"2026-2-26") -> 2026-2-26
A20: 4d | B20: Data Analytics | C20: Europe | D20: Remote | E20: Full Time | F20: Miratech | G20: Miratech: Global IT consulting firm providing digital engineering and CX services. | H20: 3+ YOE3+ years in data analysis; strong SQL, Excel; Tableau; experience with IVR or contact center data; good communication. | I20: SQL, Excel, Tableau | J20: Job Posting | K20: 46083 | L20: Departments - Data and Analytics, Budapest (Remote, Hybrid, Onsite), No keyword search, 6 months | M20: =IFERROR(__xludf.DUMMYFUNCTION("TEXT( IF(RIGHT(A20,2)=""mo"", EDATE(DATEVALUE(K20), -VALUE(REGEXEXTRACT(A20,""\d+""))), DATEVALUE(K20) - IF(RIGHT(A20,1)=""h"", VALUE(REGEXEXTRACT(A20,""\d+""))/24, IF(RIGHT(A20,1)=""d"", VALUE(REGEXEXTRACT(A20,""\d+"")), IF(RI"&"GHT(A20,1)=""w"", VALUE(REGEXEXTRACT(A20,""\d+""))*7, 0))) ) , ""YYYY-M-D"")"),"2026-2-26") -> 2026-2-26
A21: 5d | B21: Data Governance Lead | C21: Budapest, Budapest, Hungary | D21: Hybrid | E21: Full Time | F21: Sanofi | G21: SanofiNASDAQ: SNY: Develops and manufactures pharmaceuticals and vaccines for global patients. | H21: Lead global data governance, ensure data quality and compliance; manage data stewards; implement governance strategies. | I21: MDM, CI/CD, Data governance, Agile | J21: Job Posting | K21: 46083 | L21: Departments - Data and Analytics, Budapest (Remote, Hybrid, Onsite), No keyword search, 6 months | M21: =IFERROR(__xludf.DUMMYFUNCTION("TEXT( IF(RIGHT(A21,2)=""mo"", EDATE(DATEVALUE(K21), -VALUE(REGEXEXTRACT(A21,""\d+""))), DATEVALUE(K21) - IF(RIGHT(A21,1)=""h"", VALUE(REGEXEXTRACT(A21,""\d+""))/24, IF(RIGHT(A21,1)=""d"", VALUE(REGEXEXTRACT(A21,""\d+"")), IF(RI"&"GHT(A21,1)=""w"", VALUE(REGEXEXTRACT(A21,""\d+""))*7, 0))) ) , ""YYYY-M-D"")"),"2026-2-25") -> 2026-2-25
A22: 5d | B22: Lead Data Engineer | C22: Budapest, Budapest, Hungary | D22: Hybrid | E22: Full Time | F22: Morgan Stanley | G22: Morgan StanleyNYSE: MS: Provides investment banking, wealth management, and financial services. | H22: 6+ YOELead data engineer with 6+ years in data engineering, data architecture, SQL, ETL, cloud platforms (Snowflake), GenAI/AI/ML, and strong leadership. | I22: Snowflake, SQL, ETL, GenAI, LLMs, CI/CD, AI/ML tools | J22: Job Posting | K22: 46083 | L22: Departments - Data and Analytics, Budapest (Remote, Hybrid, Onsite), No keyword search, 6 months | M22: =IFERROR(__xludf.DUMMYFUNCTION("TEXT( IF(RIGHT(A22,2)=""mo"", EDATE(DATEVALUE(K22), -VALUE(REGEXEXTRACT(A22,""\d+""))), DATEVALUE(K22) - IF(RIGHT(A22,1)=""h"", VALUE(REGEXEXTRACT(A22,""\d+""))/24, IF(RIGHT(A22,1)=""d"", VALUE(REGEXEXTRACT(A22,""\d+"")), IF(RI"&"GHT(A22,1)=""w"", VALUE(REGEXEXTRACT(A22,""\d+""))*7, 0))) ) , ""YYYY-M-D"")"),"2026-2-25") -> 2026-2-25
A23: 5d | B23: AI Training Specialist | C23: North America or Europe or Asia | D23: Remote | E23: Contract | F23: Prolific | G23: Prolific: Connecting researchers with vetted participants for high-quality data collection. | H23: 0+ YOEExperience as AI trainer or similar; ability to complete paid tasks with focus for up to an hour; reliable internet; computer access; willingness to self-declare earnings; PayPal familiar; willing to take verification test. | I23: General AI Training, Image and Video Annotation, Trust and Safety, Evaluations, Red Teaming, Quality Analytics | J23: Job Posting | K23: 46083 | L23: Departments - Data and Analytics, Budapest (Remote, Hybrid, Onsite), No keyword search, 6 months | M23: =IFERROR(__xludf.DUMMYFUNCTION("TEXT( IF(RIGHT(A23,2)=""mo"", EDATE(DATEVALUE(K23), -VALUE(REGEXEXTRACT(A23,""\d+""))), DATEVALUE(K23) - IF(RIGHT(A23,1)=""h"", VALUE(REGEXEXTRACT(A23,""\d+""))/24, IF(RIGHT(A23,1)=""d"", VALUE(REGEXEXTRACT(A23,""\d+"")), IF(RI"&"GHT(A23,1)=""w"", VALUE(REGEXEXTRACT(A23,""\d+""))*7, 0))) ) , ""YYYY-M-D"")"),"2026-2-25") -> 2026-2-25
A24: 5d | B24: Product Analyst | C24: Europe | D24: Remote | E24: Contract | F24: Scentbird | G24: Scentbird: Monthly subscription service for sampling designer perfumes and colognes. | H24: Experience in product analytics and data-driven decision making. | I24: Not available | J24: Job Posting | K24: 46083 | L24: Departments - Data and Analytics, Budapest (Remote, Hybrid, Onsite), No keyword search, 6 months | M24: =IFERROR(__xludf.DUMMYFUNCTION("TEXT( IF(RIGHT(A24,2)=""mo"", EDATE(DATEVALUE(K24), -VALUE(REGEXEXTRACT(A24,""\d+""))), DATEVALUE(K24) - IF(RIGHT(A24,1)=""h"", VALUE(REGEXEXTRACT(A24,""\d+""))/24, IF(RIGHT(A24,1)=""d"", VALUE(REGEXEXTRACT(A24,""\d+"")), IF(RI"&"GHT(A24,1)=""w"", VALUE(REGEXEXTRACT(A24,""\d+""))*7, 0))) ) , ""YYYY-M-D"")"),"2026-2-25") -> 2026-2-25
A25: 6d | B25: Master Data Management Associate | C25: Budapest, Budapest, Hungary | D25: Onsite | E25: Full Time | F25: Tesco | G25: TescoLondon Stock Exchange: TSCO: Operates a global network of grocery and retail stores. | H25: 1+ YOEHigh school diploma; upper-intermediate English; Hungarian; 1-3 years relevant experience; proactivity; analytical skills; accuracy and attention to detail; effective communication. | I25: Oracle | J25: Job Posting | K25: 46083 | L25: Departments - Data and Analytics, Budapest (Remote, Hybrid, Onsite), No keyword search, 6 months | M25: =IFERROR(__xludf.DUMMYFUNCTION("TEXT( IF(RIGHT(A25,2)=""mo"", EDATE(DATEVALUE(K25), -VALUE(REGEXEXTRACT(A25,""\d+""))), DATEVALUE(K25) - IF(RIGHT(A25,1)=""h"", VALUE(REGEXEXTRACT(A25,""\d+""))/24, IF(RIGHT(A25,1)=""d"", VALUE(REGEXEXTRACT(A25,""\d+"")), IF(RI"&"GHT(A25,1)=""w"", VALUE(REGEXEXTRACT(A25,""\d+""))*7, 0))) ) , ""YYYY-M-D"")"),"2026-2-24") -> 2026-2-24
A26: 6d | B26: Data & Analytics Product Manager - Supply | C26: Budapest or Bangalore | D26: Hybrid | E26: Full Time | F26: Diageo | G26: DiageoLondon Stock Exchange: DGE: Produces and distributes premium alcoholic beverages worldwide. | H26: 4+ YOE2+ Mgmt8+ years in data/analytics; Master’s degree; 4+ years in enterprise data analytics; 2+ years leadership; expertise in predictive modelling, segmentation, ROI measurement; 2+ years in B2B product/program management. | I26: SQL, Python, R, Tableau, Power BI, Excel, ETL, Cloud data platforms | J26: Job Posting | K26: 46083 | L26: Departments - Data and Analytics, Budapest (Remote, Hybrid, Onsite), No keyword search, 6 months | M26: =IFERROR(__xludf.DUMMYFUNCTION("TEXT( IF(RIGHT(A26,2)=""mo"", EDATE(DATEVALUE(K26), -VALUE(REGEXEXTRACT(A26,""\d+""))), DATEVALUE(K26) - IF(RIGHT(A26,1)=""h"", VALUE(REGEXEXTRACT(A26,""\d+""))/24, IF(RIGHT(A26,1)=""d"", VALUE(REGEXEXTRACT(A26,""\d+"")), IF(RI"&"GHT(A26,1)=""w"", VALUE(REGEXEXTRACT(A26,""\d+""))*7, 0))) ) , ""YYYY-M-D"")"),"2026-2-24") -> 2026-2-24
A27: 6d | B27: Operációtámogatási és adatgazdagítási specialista | C27: Budapest, Budapest, Hungary | D27: Hybrid | E27: Full Time | F27: Intrum | G27: IntrumNasdaq Stockholm: INTRUM: Provides credit management and debt collection services to businesses. | H27: 1+ YOESecondary education; 1-2 years experience; precise, deadline-driven; proficient in Excel; team player; problem solving; willing to learn. Power BI and English a plus. | I27: Excel, Power BI | J27: Job Posting | K27: 46083 | L27: Departments - Data and Analytics, Budapest (Remote, Hybrid, Onsite), No keyword search, 6 months | M27: =IFERROR(__xludf.DUMMYFUNCTION("TEXT( IF(RIGHT(A27,2)=""mo"", EDATE(DATEVALUE(K27), -VALUE(REGEXEXTRACT(A27,""\d+""))), DATEVALUE(K27) - IF(RIGHT(A27,1)=""h"", VALUE(REGEXEXTRACT(A27,""\d+""))/24, IF(RIGHT(A27,1)=""d"", VALUE(REGEXEXTRACT(A27,""\d+"")), IF(RI"&"GHT(A27,1)=""w"", VALUE(REGEXEXTRACT(A27,""\d+""))*7, 0))) ) , ""YYYY-M-D"")"),"2026-2-24") -> 2026-2-24
A28: 6d | B28: R0000038368 Manager, Centralized Data & Sample Management - Poland / Spain / Hungary - FSP | C28: Madrid or Poland or Budapest | D28: Remote | E28: Full Time | F28: Parexel | G28: Parexel: Provides clinical trial management and drug development consulting services. | H28: 5+ YOEBachelor’s degree; 5+ years in Clinical Data Management or sample management; knowledge of third-party data; strong project management; communication skills; ability to work with globally distributed teams; willingness to travel. | I28: Electronic Data Capture (EDC), Rave, InForm, data management systems | J28: Job Posting | K28: 46083 | L28: Departments - Data and Analytics, Budapest (Remote, Hybrid, Onsite), No keyword search, 6 months | M28: =IFERROR(__xludf.DUMMYFUNCTION("TEXT( IF(RIGHT(A28,2)=""mo"", EDATE(DATEVALUE(K28), -VALUE(REGEXEXTRACT(A28,""\d+""))), DATEVALUE(K28) - IF(RIGHT(A28,1)=""h"", VALUE(REGEXEXTRACT(A28,""\d+""))/24, IF(RIGHT(A28,1)=""d"", VALUE(REGEXEXTRACT(A28,""\d+"")), IF(RI"&"GHT(A28,1)=""w"", VALUE(REGEXEXTRACT(A28,""\d+""))*7, 0))) ) , ""YYYY-M-D"")"),"2026-2-24") -> 2026-2-24
A29: 6d | B29: Erőmű adatelemző szakértő (Budapest, HU) | C29: Budapest or Debrecen | D29: Onsite | E29: Full Time | F29: E.ON | G29: E.ONXetra: EOAN: Operates energy networks and provides consumer energy solutions. | H29: 5+ YOEStrong analytical skills with SQL, Power BI, Python; experience in data warehousing, automation, and IT systems in energy sector. | I29: Power BI, SQL, Python, Excel Macros, Power Apps, R, RStudio, Databricks, MS Power Platform | J29: Job Posting | K29: 46083 | L29: Departments - Data and Analytics, Budapest (Remote, Hybrid, Onsite), No keyword search, 6 months | M29: =IFERROR(__xludf.DUMMYFUNCTION("TEXT( IF(RIGHT(A29,2)=""mo"", EDATE(DATEVALUE(K29), -VALUE(REGEXEXTRACT(A29,""\d+""))), DATEVALUE(K29) - IF(RIGHT(A29,1)=""h"", VALUE(REGEXEXTRACT(A29,""\d+""))/24, IF(RIGHT(A29,1)=""d"", VALUE(REGEXEXTRACT(A29,""\d+"")), IF(RI"&"GHT(A29,1)=""w"", VALUE(REGEXEXTRACT(A29,""\d+""))*7, 0))) ) , ""YYYY-M-D"")"),"2026-2-24") -> 2026-2-24
A30: 1w | B30: Enterprise Data Office - Production Support Senior Analyst | C30: Budapest, Budapest, Hungary | D30: Hybrid | E30: Full Time | F30: Citi | G30: CitiNYSE: C: Global financial institution providing retail, corporate, and investment banking services. | H30: 4+ YOE4-6 years in production support; knowledge of ServiceNow, JIRA, Confluence; MS Office; SharePoint a plus; strong incident/problem management; English fluency. | I30: ServiceNow, Atlassian JIRA, Confluence, Agile, Microsoft Word, Microsoft Excel, Microsoft PowerPoint, MS Visio, SharePoint | J30: Job Posting | K30: 46083 | L30: Departments - Data and Analytics, Budapest (Remote, Hybrid, Onsite), No keyword search, 6 months | M30: =IFERROR(__xludf.DUMMYFUNCTION("TEXT( IF(RIGHT(A30,2)=""mo"", EDATE(DATEVALUE(K30), -VALUE(REGEXEXTRACT(A30,""\d+""))), DATEVALUE(K30) - IF(RIGHT(A30,1)=""h"", VALUE(REGEXEXTRACT(A30,""\d+""))/24, IF(RIGHT(A30,1)=""d"", VALUE(REGEXEXTRACT(A30,""\d+"")), IF(RI"&"GHT(A30,1)=""w"", VALUE(REGEXEXTRACT(A30,""\d+""))*7, 0))) ) , ""YYYY-M-D"")"),"2026-2-23") -> 2026-2-23
A31: 1w | B31: AI Data Specialist - Hungarian | C31: Budapest, Budapest, Hungary | D31: Remote | E31: Contract, Part Time | F31: RWS | G31: RWSLondon Stock Exchange: RWS: Provides global translation, intellectual property, and AI language solutions. | H31: Freelance, part-time role for Hungarian language data work; remote; tasks include data collection, evaluation, annotation; need Hungarian native level and English proficiency; flexible schedule. | I31: Data annotation, Labeling | J31: Job Posting | K31: 46083 | L31: Departments - Data and Analytics, Budapest (Remote, Hybrid, Onsite), No keyword search, 6 months | M31: =IFERROR(__xludf.DUMMYFUNCTION("TEXT( IF(RIGHT(A31,2)=""mo"", EDATE(DATEVALUE(K31), -VALUE(REGEXEXTRACT(A31,""\d+""))), DATEVALUE(K31) - IF(RIGHT(A31,1)=""h"", VALUE(REGEXEXTRACT(A31,""\d+""))/24, IF(RIGHT(A31,1)=""d"", VALUE(REGEXEXTRACT(A31,""\d+"")), IF(RI"&"GHT(A31,1)=""w"", VALUE(REGEXEXTRACT(A31,""\d+""))*7, 0))) ) , ""YYYY-M-D"")"),"2026-2-23") -> 2026-2-23
A32: 1w | B32: SEO Expert | C32: Budapest, Budapest, Hungary | D32: Remote | E32: Full Time | F32: Hustler Marketing | G32: Hustler Marketing: Provides data-driven email and SMS marketing for eCommerce brands. | H32: 4+ YOE5 years+ SEO for ecommerce; client-facing; agency/freelance background; strong technical SEO; experience with Shopify/WooCommerce/Magento; English communication; remote work. | I32: Ahrefs, SEMrush, Screaming Frog, Google Analytics, Google Search Console, Shopify, WooCommerce, Magento, BigCommerce | J32: Job Posting | K32: 46083 | L32: Departments - Data and Analytics, Budapest (Remote, Hybrid, Onsite), No keyword search, 6 months | M32: =IFERROR(__xludf.DUMMYFUNCTION("TEXT( IF(RIGHT(A32,2)=""mo"", EDATE(DATEVALUE(K32), -VALUE(REGEXEXTRACT(A32,""\d+""))), DATEVALUE(K32) - IF(RIGHT(A32,1)=""h"", VALUE(REGEXEXTRACT(A32,""\d+""))/24, IF(RIGHT(A32,1)=""d"", VALUE(REGEXEXTRACT(A32,""\d+"")), IF(RI"&"GHT(A32,1)=""w"", VALUE(REGEXEXTRACT(A32,""\d+""))*7, 0))) ) , ""YYYY-M-D"")"),"2026-2-23") -> 2026-2-23
A33: 1w | B33: Senior Data Management Expert | C33: Budapest, Budapest, Hungary | D33: Hybrid | E33: Full Time | F33: YouGov | G33: YouGovLondon Stock Exchange: YOU: International online market research and data analytics technology. | H33: Advanced Excel with macros; strong database management; fluent English and Hungarian; UNIX basics; SPSS; MS Access; Budapest-based hybrid role. | I33: Microsoft Excel, UNIX, SPSS, MS Access | J33: Job Posting | K33: 46083 | L33: Departments - Data and Analytics, Budapest (Remote, Hybrid, Onsite), No keyword search, 6 months | M33: =IFERROR(__xludf.DUMMYFUNCTION("TEXT( IF(RIGHT(A33,2)=""mo"", EDATE(DATEVALUE(K33), -VALUE(REGEXEXTRACT(A33,""\d+""))), DATEVALUE(K33) - IF(RIGHT(A33,1)=""h"", VALUE(REGEXEXTRACT(A33,""\d+""))/24, IF(RIGHT(A33,1)=""d"", VALUE(REGEXEXTRACT(A33,""\d+"")), IF(RI"&"GHT(A33,1)=""w"", VALUE(REGEXEXTRACT(A33,""\d+""))*7, 0))) ) , ""YYYY-M-D"")"),"2026-2-23") -> 2026-2-23
A34: 1w | B34: Senior Data Management Expert | C34: Budapest, Budapest, Hungary | D34: Hybrid | E34: Full Time | F34: YouGov | G34: YouGovLondon Stock Exchange: YOU: Provides global consumer data and market research insights. | H34: Advanced Excel, strong database management, English and Hungarian, UNIX, SPSS, MS Access; hybrid Budapest; 3 days in office. | I34: Microsoft Excel, UNIX, SPSS, MS Access, Macros | J34: Job Posting | K34: 46083 | L34: Departments - Data and Analytics, Budapest (Remote, Hybrid, Onsite), No keyword search, 6 months | M34: =IFERROR(__xludf.DUMMYFUNCTION("TEXT( IF(RIGHT(A34,2)=""mo"", EDATE(DATEVALUE(K34), -VALUE(REGEXEXTRACT(A34,""\d+""))), DATEVALUE(K34) - IF(RIGHT(A34,1)=""h"", VALUE(REGEXEXTRACT(A34,""\d+""))/24, IF(RIGHT(A34,1)=""d"", VALUE(REGEXEXTRACT(A34,""\d+"")), IF(RI"&"GHT(A34,1)=""w"", VALUE(REGEXEXTRACT(A34,""\d+""))*7, 0))) ) , ""YYYY-M-D"")"),"2026-2-23") -> 2026-2-23
A35: 1w | B35: Downstream Business Analyst Expert | C35: Budapest, Budapest, Hungary | D35: Onsite | E35: Full Time | F35: MOL Group | G35: MOL GroupBudapest Stock Exchange: MOL: Integrated international providing oil and gas products. | H35: 2+ YOEUniversity/college degree in finance/economics; 0-2 years’ experience; highly proficient in Excel; fluent English; strong financial/performance analysis; problem solving; structured thinking; collaborative. | I35: Microsoft Excel | J35: Job Posting | K35: 46083 | L35: Departments - Data and Analytics, Budapest (Remote, Hybrid, Onsite), No keyword search, 6 months | M35: =IFERROR(__xludf.DUMMYFUNCTION("TEXT( IF(RIGHT(A35,2)=""mo"", EDATE(DATEVALUE(K35), -VALUE(REGEXEXTRACT(A35,""\d+""))), DATEVALUE(K35) - IF(RIGHT(A35,1)=""h"", VALUE(REGEXEXTRACT(A35,""\d+""))/24, IF(RIGHT(A35,1)=""d"", VALUE(REGEXEXTRACT(A35,""\d+"")), IF(RI"&"GHT(A35,1)=""w"", VALUE(REGEXEXTRACT(A35,""\d+""))*7, 0))) ) , ""YYYY-M-D"")"),"2026-2-23") -> 2026-2-23
A36: 1w | B36: Finance Systems Manager | C36: Budapest, Budapest, Hungary | D36: Onsite | E36: Full Time | F36: Danaher | G36: DanaherNYSE: DHR: Global innovator in diagnostics, life sciences, and biotechnology solutions. | H36: BS/MS in Business, Finance, IT, Project or similar; strong QlikSense; proven ability to lead global cross-functional teams; analytical, problem-solving, and communication skills. | I36: QlikSense | J36: Job Posting | K36: 46083 | L36: Departments - Data and Analytics, Budapest (Remote, Hybrid, Onsite), No keyword search, 6 months | M36: =IFERROR(__xludf.DUMMYFUNCTION("TEXT( IF(RIGHT(A36,2)=""mo"", EDATE(DATEVALUE(K36), -VALUE(REGEXEXTRACT(A36,""\d+""))), DATEVALUE(K36) - IF(RIGHT(A36,1)=""h"", VALUE(REGEXEXTRACT(A36,""\d+""))/24, IF(RIGHT(A36,1)=""d"", VALUE(REGEXEXTRACT(A36,""\d+"")), IF(RI"&"GHT(A36,1)=""w"", VALUE(REGEXEXTRACT(A36,""\d+""))*7, 0))) ) , ""YYYY-M-D"")"),"2026-2-23") -> 2026-2-23
A37: 1w | B37: Software Engineer, Data Platform | C37: Europe | D37: Remote | E37: Full Time | F37: Pagos | G37: Pagos: Software platform that optimizes business payment infrastructure and data. | H37: 8+ YOE8+ years of software engineering with a focus on data engineering; strong backend, APIs, and data pipelines; experience with cloud platforms and data technologies. | I37: SQL, REST, gRPC, AWS, GCP, Azure, Redshift, Clickhouse, Trino, StarRocks, Apache Iceberg, Postgres, S3, EMR, Glue, Kinesis, Athena, DBT | J37: Job Posting | K37: 46083 | L37: Departments - Data and Analytics, Budapest (Remote, Hybrid, Onsite), No keyword search, 6 months | M37: =IFERROR(__xludf.DUMMYFUNCTION("TEXT( IF(RIGHT(A37,2)=""mo"", EDATE(DATEVALUE(K37), -VALUE(REGEXEXTRACT(A37,""\d+""))), DATEVALUE(K37) - IF(RIGHT(A37,1)=""h"", VALUE(REGEXEXTRACT(A37,""\d+""))/24, IF(RIGHT(A37,1)=""d"", VALUE(REGEXEXTRACT(A37,""\d+"")), IF(RI"&"GHT(A37,1)=""w"", VALUE(REGEXEXTRACT(A37,""\d+""))*7, 0))) ) , ""YYYY-M-D"")"),"2026-2-23") -> 2026-2-23
A38: 1w | B38: Data engineer trainee | C38: Budapest, Budapest, Hungary | D38: Hybrid | E38: Internship | F38: Bosch | G38: Bosch: Global provider of technology for mobility and smart homes. | H38: Internship student with programming knowledge in Python and SQL; basic data science understanding; 20 hours/week minimum; Hungarian language; Git familiarity; English at least intermediate. | I38: Python, SQL, Pandas, Numpy, Scipy, Matplotlib, TensorFlow, Git | J38: Job Posting | K38: 46083 | L38: Departments - Data and Analytics, Budapest (Remote, Hybrid, Onsite), No keyword search, 6 months | M38: =IFERROR(__xludf.DUMMYFUNCTION("TEXT( IF(RIGHT(A38,2)=""mo"", EDATE(DATEVALUE(K38), -VALUE(REGEXEXTRACT(A38,""\d+""))), DATEVALUE(K38) - IF(RIGHT(A38,1)=""h"", VALUE(REGEXEXTRACT(A38,""\d+""))/24, IF(RIGHT(A38,1)=""d"", VALUE(REGEXEXTRACT(A38,""\d+"")), IF(RI"&"GHT(A38,1)=""w"", VALUE(REGEXEXTRACT(A38,""\d+""))*7, 0))) ) , ""YYYY-M-D"")"),"2026-2-23") -> 2026-2-23
A39: 1w | B39: Junior Operations Performance Manager (Budapest, HU, H-1095) | C39: Budapest, Budapest, Hungary | D39: Onsite | E39: Full Time | F39: Wizz Air | G39: Wizz AirLondon Stock Exchange: WIZZ: Ultra-low-cost airline offering point-to-point passenger flights. | H39: 1+ YOE1-3+ years in data analysis; experience with data visualization; English fluency. | I39: MS Excel, Power Pivot, Power Query, Power BI, SQL, DAX, Data Visualization | J39: Job Posting | K39: 46083 | L39: Departments - Data and Analytics, Budapest (Remote, Hybrid, Onsite), No keyword search, 6 months | M39: =IFERROR(__xludf.DUMMYFUNCTION("TEXT( IF(RIGHT(A39,2)=""mo"", EDATE(DATEVALUE(K39), -VALUE(REGEXEXTRACT(A39,""\d+""))), DATEVALUE(K39) - IF(RIGHT(A39,1)=""h"", VALUE(REGEXEXTRACT(A39,""\d+""))/24, IF(RIGHT(A39,1)=""d"", VALUE(REGEXEXTRACT(A39,""\d+"")), IF(RI"&"GHT(A39,1)=""w"", VALUE(REGEXEXTRACT(A39,""\d+""))*7, 0))) ) , ""YYYY-M-D"")"),"2026-2-23") -> 2026-2-23
A40: 1w | B40: Senior Data Platform Engineer | C40: Budapest, Budapest, Hungary | D40: Onsite | E40: Full Time | F40: GSCF | G40: GSCF: Provides technology-enabled working capital and supply chain finance solutions. | H40: 5+ YOE5+ years SQL, 3+ years data warehouse design/ops, 3+ years cloud (AWS/Azure/GCP), experience with Airflow/Dagster, 5+ years programming (Python/Java/Scala), experience with Snowflake/Redshift/Databricks/BigQuery | I40: SQL, Airflow, Dagster, Python, Java, Scala, Snowflake, Redshift, Databricks, BigQuery, dbt, Terraform, Power BI, Tableau, Power Query, DAX | J40: Job Posting | K40: 46083 | L40: Departments - Data and Analytics, Budapest (Remote, Hybrid, Onsite), No keyword search, 6 months | M40: =IFERROR(__xludf.DUMMYFUNCTION("TEXT( IF(RIGHT(A40,2)=""mo"", EDATE(DATEVALUE(K40), -VALUE(REGEXEXTRACT(A40,""\d+""))), DATEVALUE(K40) - IF(RIGHT(A40,1)=""h"", VALUE(REGEXEXTRACT(A40,""\d+""))/24, IF(RIGHT(A40,1)=""d"", VALUE(REGEXEXTRACT(A40,""\d+"")), IF(RI"&"GHT(A40,1)=""w"", VALUE(REGEXEXTRACT(A40,""\d+""))*7, 0))) ) , ""YYYY-M-D"")"),"2026-2-23") -> 2026-2-23
A41: 1w | B41: English Speaking Master Data Specialist (Budapest, HU, 1095) | C41: Budapest, Budapest, Hungary | D41: Hybrid | E41: Full Time | F41: Computacenter | G41: ComputacenterLondon Stock Exchange: CCC: Provides IT infrastructure services and technology products to organizations. | H41: 1+ YOEEnglish fluent; experience with master data in IT; hardware knowledge; familiarity with ServiceNow or ITSM tools; strong Excel (Macro, VBA); SQL; ability to work in virtual teams and manage customer expectations. | I41: ServiceNow, SQL, Excel, VBA, SAP, CRM/ERP systems | J41: Job Posting | K41: 46083 | L41: Departments - Data and Analytics, Budapest (Remote, Hybrid, Onsite), No keyword search, 6 months | M41: =IFERROR(__xludf.DUMMYFUNCTION("TEXT( IF(RIGHT(A41,2)=""mo"", EDATE(DATEVALUE(K41), -VALUE(REGEXEXTRACT(A41,""\d+""))), DATEVALUE(K41) - IF(RIGHT(A41,1)=""h"", VALUE(REGEXEXTRACT(A41,""\d+""))/24, IF(RIGHT(A41,1)=""d"", VALUE(REGEXEXTRACT(A41,""\d+"")), IF(RI"&"GHT(A41,1)=""w"", VALUE(REGEXEXTRACT(A41,""\d+""))*7, 0))) ) , ""YYYY-M-D"")"),"2026-2-23") -> 2026-2-23
A42: 1w | B42: Tech Lead (Database Operation) (Törökbálint, HU, 2045) | C42: Törökbálint, Budapest, Hungary | D42: Onsite | E42: Full Time | F42: Yettel | G42: Yettel: Provides mobile network, internet, and television services to consumers. | H42: Experience as Database Administrator and Team Lead; strong MySQL and MS SQL Server expertise; hands-on DB development; HA/DR and performance tuning; leadership and vendor coordination. | I42: MSSQL, MySQL, Oracle, PostgreSQL, Redis, Dynatrace, CI/CD | J42: Job Posting | K42: 46083 | L42: Departments - Data and Analytics, Budapest (Remote, Hybrid, Onsite), No keyword search, 6 months | M42: =IFERROR(__xludf.DUMMYFUNCTION("TEXT( IF(RIGHT(A42,2)=""mo"", EDATE(DATEVALUE(K42), -VALUE(REGEXEXTRACT(A42,""\d+""))), DATEVALUE(K42) - IF(RIGHT(A42,1)=""h"", VALUE(REGEXEXTRACT(A42,""\d+""))/24, IF(RIGHT(A42,1)=""d"", VALUE(REGEXEXTRACT(A42,""\d+"")), IF(RI"&"GHT(A42,1)=""w"", VALUE(REGEXEXTRACT(A42,""\d+""))*7, 0))) ) , ""YYYY-M-D"")"),"2026-2-23") -> 2026-2-23
A43: 2w | B43: BI Analyst Team Lead | C43: Budapest, Budapest, Hungary | D43: Onsite | E43: Full Time | F43: Sony | G43: SonyNew York Stock Exchange: SONY: Manufactures consumer electronics and produces gaming and entertainment content. | H43: 2+ YOE2+ MgmtLead a BI team (3–5 people); develop Power BI dashboards; manage stakeholder expectations; ensure data quality and timely insights. | I43: Power BI, SQL, Python, Databricks, MS Power Automate | J43: Job Posting | K43: 46083 | L43: Departments - Data and Analytics, Budapest (Remote, Hybrid, Onsite), No keyword search, 6 months | M43: =IFERROR(__xludf.DUMMYFUNCTION("TEXT( IF(RIGHT(A43,2)=""mo"", EDATE(DATEVALUE(K43), -VALUE(REGEXEXTRACT(A43,""\d+""))), DATEVALUE(K43) - IF(RIGHT(A43,1)=""h"", VALUE(REGEXEXTRACT(A43,""\d+""))/24, IF(RIGHT(A43,1)=""d"", VALUE(REGEXEXTRACT(A43,""\d+"")), IF(RI"&"GHT(A43,1)=""w"", VALUE(REGEXEXTRACT(A43,""\d+""))*7, 0))) ) , ""YYYY-M-D"")"),"2026-2-16") -> 2026-2-16
A44: 2w | B44: Information Management Officer | C44: Kyiv or Budapest | D44: Onsite | E44: Full Time | F44: UNHCR | G44: UNHCR: Protects and supports refugees and displaced people globally. | H44: 5+ YOE5+ years in data or statistics; degree in Social Science, Statistics, Information Management, Geography/GIS; experience in humanitarian context; strong data management, analytics, and GIS skills. | I44: ArcGIS, Power BI, Kobo Toolbox, ActivityInfo, RAIS+, SIDAR | J44: Job Posting | K44: 46083 | L44: Departments - Data and Analytics, Budapest (Remote, Hybrid, Onsite), No keyword search, 6 months | M44: =IFERROR(__xludf.DUMMYFUNCTION("TEXT( IF(RIGHT(A44,2)=""mo"", EDATE(DATEVALUE(K44), -VALUE(REGEXEXTRACT(A44,""\d+""))), DATEVALUE(K44) - IF(RIGHT(A44,1)=""h"", VALUE(REGEXEXTRACT(A44,""\d+""))/24, IF(RIGHT(A44,1)=""d"", VALUE(REGEXEXTRACT(A44,""\d+"")), IF(RI"&"GHT(A44,1)=""w"", VALUE(REGEXEXTRACT(A44,""\d+""))*7, 0))) ) , ""YYYY-M-D"")"),"2026-2-16") -> 2026-2-16
A45: 2w | B45: BI Analyst Team Lead | C45: Budapest, Budapest, Hungary | D45: Onsite | E45: Full Time | F45: Sony Europe | G45: Sony EuropeNYSE: SONY: Sells and supports consumer electronics and entertainment technology products. | H45: 3+ YOE2+ MgmtLeadership of a 3–5 person BI team; Power BI, SQL, Python; stakeholder management; Pan-European stakeholder experience. | I45: Power BI, SQL, Python, Databricks, Power Automate, MS SQL | J45: Job Posting | K45: 46083 | L45: Departments - Data and Analytics, Budapest (Remote, Hybrid, Onsite), No keyword search, 6 months | M45: =IFERROR(__xludf.DUMMYFUNCTION("TEXT( IF(RIGHT(A45,2)=""mo"", EDATE(DATEVALUE(K45), -VALUE(REGEXEXTRACT(A45,""\d+""))), DATEVALUE(K45) - IF(RIGHT(A45,1)=""h"", VALUE(REGEXEXTRACT(A45,""\d+""))/24, IF(RIGHT(A45,1)=""d"", VALUE(REGEXEXTRACT(A45,""\d+"")), IF(RI"&"GHT(A45,1)=""w"", VALUE(REGEXEXTRACT(A45,""\d+""))*7, 0))) ) , ""YYYY-M-D"")"),"2026-2-16") -> 2026-2-16
A46: 2w | B46: Data Engineer | C46: Romania or Europe | D46: Remote | E46: Full Time | F46: Suvoda | G46: Suvoda: Provide software and services for global clinical trial management. | H46: 4+ YOE4+ years data engineering; AWS data lake tech; Python/SQL; data mesh understanding; CI/CD; ETL/ELT. | I46: AWS, Python, SQL, Airflow, Terraform, CloudFormation, PySpark, Kafka, Kinesis, S3, Glue, Lake Formation, Athena, Redshift | J46: Job Posting | K46: 46083 | L46: Departments - Data and Analytics, Budapest (Remote, Hybrid, Onsite), No keyword search, 6 months | M46: =IFERROR(__xludf.DUMMYFUNCTION("TEXT( IF(RIGHT(A46,2)=""mo"", EDATE(DATEVALUE(K46), -VALUE(REGEXEXTRACT(A46,""\d+""))), DATEVALUE(K46) - IF(RIGHT(A46,1)=""h"", VALUE(REGEXEXTRACT(A46,""\d+""))/24, IF(RIGHT(A46,1)=""d"", VALUE(REGEXEXTRACT(A46,""\d+"")), IF(RI"&"GHT(A46,1)=""w"", VALUE(REGEXEXTRACT(A46,""\d+""))*7, 0))) ) , ""YYYY-M-D"")"),"2026-2-16") -> 2026-2-16
A47: 2w | B47: Senior Data Engineer (ADB + Python) | C47: Armenia or Bulgaria or Georgia or Hungary or Lithuania or Poland or Portugal or Romania or Uzbekistan | D47: Remote | E47: All Commitments Available | F47: Exadel | G47: Exadel: Provides global software engineering and digital transformation services. | H47: 5+ YOE5+ years of software development; expert in Apache Spark (Databricks/Azure Synapse/Fabric); Python with Pandas/Polars; Delta Tables; data processing and scalable microservices; strong problem-solving; ability to work independently and with teams. | I47: Apache Spark, Databricks, Azure Synapse, Azure Fabric, Python, Pandas, Polars, Parquet, Delta Tables, LangGraph, LangChain, RAG Pipelines, Multi-modal LLMs, MongoDB, Azure SQL, FastAPI, Docker, Kubernetes | J47: Job Posting | K47: 46083 | L47: Departments - Data and Analytics, Budapest (Remote, Hybrid, Onsite), No keyword search, 6 months | M47: =IFERROR(__xludf.DUMMYFUNCTION("TEXT( IF(RIGHT(A47,2)=""mo"", EDATE(DATEVALUE(K47), -VALUE(REGEXEXTRACT(A47,""\d+""))), DATEVALUE(K47) - IF(RIGHT(A47,1)=""h"", VALUE(REGEXEXTRACT(A47,""\d+""))/24, IF(RIGHT(A47,1)=""d"", VALUE(REGEXEXTRACT(A47,""\d+"")), IF(RI"&"GHT(A47,1)=""w"", VALUE(REGEXEXTRACT(A47,""\d+""))*7, 0))) ) , ""YYYY-M-D"")"),"2026-2-16") -> 2026-2-16
A48: 2w | B48: Clinical Data Manager | C48: Hungary | D48: Remote | E48: Full Time | F48: Clario | G48: Clario: Provides digital endpoint data solutions for clinical trials. | H48: 1+ YOEBachelor’s degree in Computer Science or Life Sciences (or related field); 1+ year in a similar pharma/CRO role; knowledge of relational databases and data validation; SAS knowledge desirable; proficient with Word/Excel/Access; strong documentation and communication skills. | I48: SAS, Relational Databases, Microsoft Word, Microsoft Excel, Microsoft Access | J48: Job Posting | K48: 46083 | L48: Departments - Data and Analytics, Budapest (Remote, Hybrid, Onsite), No keyword search, 6 months | M48: =IFERROR(__xludf.DUMMYFUNCTION("TEXT( IF(RIGHT(A48,2)=""mo"", EDATE(DATEVALUE(K48), -VALUE(REGEXEXTRACT(A48,""\d+""))), DATEVALUE(K48) - IF(RIGHT(A48,1)=""h"", VALUE(REGEXEXTRACT(A48,""\d+""))/24, IF(RIGHT(A48,1)=""d"", VALUE(REGEXEXTRACT(A48,""\d+"")), IF(RI"&"GHT(A48,1)=""w"", VALUE(REGEXEXTRACT(A48,""\d+""))*7, 0))) ) , ""YYYY-M-D"")"),"2026-2-16") -> 2026-2-16
A49: 2w | B49: Data Acquisition Expert (eSource Specialist) (m/w/d) - Homebased | C49: Frankfurt or Budapest or Espoo or Madrid or Reading or Dublin or London or Milan or Rome or Turku or Barcelona or Porto Salvo | D49: Remote | E49: Full Time | F49: IQVIA | G49: IQVIANYSE: IQV: Global provider of clinical research and healthcare data analytics. | H49: 5+ YOE5+ years in clinical data management and EHR/EDC integration; strong knowledge of EDC, FHIR, and clinical trial processes; excellent communication and collaboration skills. | I49: FHIR, EHR, EDC, eCRF | J49: Job Posting | K49: 46083 | L49: Departments - Data and Analytics, Budapest (Remote, Hybrid, Onsite), No keyword search, 6 months | M49: =IFERROR(__xludf.DUMMYFUNCTION("TEXT( IF(RIGHT(A49,2)=""mo"", EDATE(DATEVALUE(K49), -VALUE(REGEXEXTRACT(A49,""\d+""))), DATEVALUE(K49) - IF(RIGHT(A49,1)=""h"", VALUE(REGEXEXTRACT(A49,""\d+""))/24, IF(RIGHT(A49,1)=""d"", VALUE(REGEXEXTRACT(A49,""\d+"")), IF(RI"&"GHT(A49,1)=""w"", VALUE(REGEXEXTRACT(A49,""\d+""))*7, 0))) ) , ""YYYY-M-D"")"),"2026-2-16") -> 2026-2-16
A50: 2w | B50: Junior Operations Analyst- Data Platforms | C50: Budapest, Budapest, Hungary | D50: Hybrid | E50: Full Time | F50: NN Group | G50: NN GroupEuronext Amsterdam: NN: Offers life insurance, pensions, and investment management services globally. | H50: 0+ YOEBachelor’s in Finance or Economics; strong Excel; SQL a plus; English proficiency; proactive, detail-oriented; independent and collaborative. | I50: Databricks, Excel, SQL | J50: Job Posting | K50: 46083 | L50: Departments - Data and Analytics, Budapest (Remote, Hybrid, Onsite), No keyword search, 6 months | M50: =IFERROR(__xludf.DUMMYFUNCTION("TEXT( IF(RIGHT(A50,2)=""mo"", EDATE(DATEVALUE(K50), -VALUE(REGEXEXTRACT(A50,""\d+""))), DATEVALUE(K50) - IF(RIGHT(A50,1)=""h"", VALUE(REGEXEXTRACT(A50,""\d+""))/24, IF(RIGHT(A50,1)=""d"", VALUE(REGEXEXTRACT(A50,""\d+"")), IF(RI"&"GHT(A50,1)=""w"", VALUE(REGEXEXTRACT(A50,""\d+""))*7, 0))) ) , ""YYYY-M-D"")"),"2026-2-16") -> 2026-2-16
A51: 2w | B51: Payroll Specialist | C51: Budapest or Prague or Warsaw | D51: Hybrid | E51: Full Time | F51: Johnson Controls | G51: Johnson ControlsNYSE: JCI: Provides energy-efficient building automation, HVAC, and fire security systems. | H51: Data-focused analyst role supporting UK & Ireland payroll data with external partners; strong Excel skills and English communication; early-career welcome. | I51: Microsoft Excel, Payroll systems, Data analysis tools | J51: Job Posting | K51: 46083 | L51: Departments - Data and Analytics, Budapest (Remote, Hybrid, Onsite), No keyword search, 6 months | M51: =IFERROR(__xludf.DUMMYFUNCTION("TEXT( IF(RIGHT(A51,2)=""mo"", EDATE(DATEVALUE(K51), -VALUE(REGEXEXTRACT(A51,""\d+""))), DATEVALUE(K51) - IF(RIGHT(A51,1)=""h"", VALUE(REGEXEXTRACT(A51,""\d+""))/24, IF(RIGHT(A51,1)=""d"", VALUE(REGEXEXTRACT(A51,""\d+"")), IF(RI"&"GHT(A51,1)=""w"", VALUE(REGEXEXTRACT(A51,""\d+""))*7, 0))) ) , ""YYYY-M-D"")"),"2026-2-16") -> 2026-2-16
A52: 2w | B52: Linguistic Engineer EU | C52: Europe | D52: Remote | E52: Full Time | F52: Smartling | G52: Smartling: Provides cloud-based translation software and professional localization services. | H52: 5+ YOE5+ years in linguistic engineering or language data science; expert linguistics; Python; data science techniques; NLP; notebooks/terminals. | I52: Python, SQL, Looker, SageMaker, Athena, Spark, S3 | J52: Job Posting | K52: 46083 | L52: Departments - Data and Analytics, Budapest (Remote, Hybrid, Onsite), No keyword search, 6 months | M52: =IFERROR(__xludf.DUMMYFUNCTION("TEXT( IF(RIGHT(A52,2)=""mo"", EDATE(DATEVALUE(K52), -VALUE(REGEXEXTRACT(A52,""\d+""))), DATEVALUE(K52) - IF(RIGHT(A52,1)=""h"", VALUE(REGEXEXTRACT(A52,""\d+""))/24, IF(RIGHT(A52,1)=""d"", VALUE(REGEXEXTRACT(A52,""\d+"")), IF(RI"&"GHT(A52,1)=""w"", VALUE(REGEXEXTRACT(A52,""\d+""))*7, 0))) ) , ""YYYY-M-D"")"),"2026-2-16") -> 2026-2-16
A53: 2w | B53: Senior Database Administrator | C53: Europe | D53: Remote | E53: Full Time | F53: Cloudbeds | G53: Cloudbeds: Cloud-based management platform for independent hospitality businesses. | H53: 5+ YOE5+ years as a Database Administrator with AWS Aurora MySQL/PostgreSQL; strong SQL, performance tuning, and cloud experience. | I53: Amazon Aurora MySQL, PostgreSQL, MySQL, SQL, AWS, DMS, Kinesis, Kafka, Percona, Liquibase, Doctrine, Alembic | J53: Job Posting | K53: 46083 | L53: Departments - Data and Analytics, Budapest (Remote, Hybrid, Onsite), No keyword search, 6 months | M53: =IFERROR(__xludf.DUMMYFUNCTION("TEXT( IF(RIGHT(A53,2)=""mo"", EDATE(DATEVALUE(K53), -VALUE(REGEXEXTRACT(A53,""\d+""))), DATEVALUE(K53) - IF(RIGHT(A53,1)=""h"", VALUE(REGEXEXTRACT(A53,""\d+""))/24, IF(RIGHT(A53,1)=""d"", VALUE(REGEXEXTRACT(A53,""\d+"")), IF(RI"&"GHT(A53,1)=""w"", VALUE(REGEXEXTRACT(A53,""\d+""))*7, 0))) ) , ""YYYY-M-D"")"),"2026-2-16") -> 2026-2-16
A54: 2w | B54: Senior Data Engineer (Budapest, HU) | C54: Budapest, Budapest, Hungary | D54: Hybrid | E54: Full Time | F54: Capgemini | G54: CapgeminiEuronext Paris: CAP: Global provider of IT consulting and digital transformation services. | H54: 10+ YOE10+ years in data engineering or related roles; strong SQL, data modelling, ETL; cloud platforms (Snowflake); Python and scripting; GenAI/AI/LLMs experience; leadership experience; finance domain knowledge. | I54: Snowflake, Power BI, Apache Airflow, OLAP, Python, Shell scripting | J54: Job Posting | K54: 46083 | L54: Departments - Data and Analytics, Budapest (Remote, Hybrid, Onsite), No keyword search, 6 months | M54: =IFERROR(__xludf.DUMMYFUNCTION("TEXT( IF(RIGHT(A54,2)=""mo"", EDATE(DATEVALUE(K54), -VALUE(REGEXEXTRACT(A54,""\d+""))), DATEVALUE(K54) - IF(RIGHT(A54,1)=""h"", VALUE(REGEXEXTRACT(A54,""\d+""))/24, IF(RIGHT(A54,1)=""d"", VALUE(REGEXEXTRACT(A54,""\d+"")), IF(RI"&"GHT(A54,1)=""w"", VALUE(REGEXEXTRACT(A54,""\d+""))*7, 0))) ) , ""YYYY-M-D"")"),"2026-2-16") -> 2026-2-16
A55: 2w | B55: Data Scientist (774364) | C55: Budapest, Budapest, Hungary | D55: Hybrid | E55: Full Time | F55: Ericsson | G55: EricssonNasdaq Stockholm: ERIC: Provides telecommunications equipment, software, and managed network services. | H55: BS or MS in Computer Science/Data Science/Statistics; ML/DL/NLP/LLMs; Python/PySpark; SQL; AWS SageMaker/Glue/Lambda; data analysis; collaboration. | I55: Python, PySpark, SQL, AWS SageMaker, Glue, Lambda | J55: Job Posting | K55: 46083 | L55: Departments - Data and Analytics, Budapest (Remote, Hybrid, Onsite), No keyword search, 6 months | M55: =IFERROR(__xludf.DUMMYFUNCTION("TEXT( IF(RIGHT(A55,2)=""mo"", EDATE(DATEVALUE(K55), -VALUE(REGEXEXTRACT(A55,""\d+""))), DATEVALUE(K55) - IF(RIGHT(A55,1)=""h"", VALUE(REGEXEXTRACT(A55,""\d+""))/24, IF(RIGHT(A55,1)=""d"", VALUE(REGEXEXTRACT(A55,""\d+"")), IF(RI"&"GHT(A55,1)=""w"", VALUE(REGEXEXTRACT(A55,""\d+""))*7, 0))) ) , ""YYYY-M-D"")"),"2026-2-16") -> 2026-2-16
A56: 2w | B56: Specialist - Master Data Management | C56: Budapest, Budapest, Hungary | D56: Onsite | E56: Full Time | F56: Avis Budget Group | G56: Avis Budget GroupNASDAQ: CAR: Provides vehicle rental and car sharing services globally. | H56: Proficient in Hungarian and English; shared service experience preferred; strong admin, problem-solving, and detail-oriented skills; proficient in MS Office, especially Excel. | I56: Microsoft Excel, Microsoft Office | J56: Job Posting | K56: 46083 | L56: Departments - Data and Analytics, Budapest (Remote, Hybrid, Onsite), No keyword search, 6 months | M56: =IFERROR(__xludf.DUMMYFUNCTION("TEXT( IF(RIGHT(A56,2)=""mo"", EDATE(DATEVALUE(K56), -VALUE(REGEXEXTRACT(A56,""\d+""))), DATEVALUE(K56) - IF(RIGHT(A56,1)=""h"", VALUE(REGEXEXTRACT(A56,""\d+""))/24, IF(RIGHT(A56,1)=""d"", VALUE(REGEXEXTRACT(A56,""\d+"")), IF(RI"&"GHT(A56,1)=""w"", VALUE(REGEXEXTRACT(A56,""\d+""))*7, 0))) ) , ""YYYY-M-D"")"),"2026-2-16") -> 2026-2-16
A57: 2w | B57: Data Analyst | C57: Budapest or Pécs | D57: Hybrid | E57: Full Time | F57: Harman | G57: Harman: Designs and engineers connected products for automakers and consumers. | H57: 3+ YOE3+ years in data warehousing/analytics; BI tools (Power BI, Qlik Sense, Tableau); Snowflake; hybrid work; supply chain knowledge. | I57: Snowflake, Power BI, Qlik Sense, Excel, Tableau | J57: Job Posting | K57: 46083 | L57: Departments - Data and Analytics, Budapest (Remote, Hybrid, Onsite), No keyword search, 6 months | M57: =IFERROR(__xludf.DUMMYFUNCTION("TEXT( IF(RIGHT(A57,2)=""mo"", EDATE(DATEVALUE(K57), -VALUE(REGEXEXTRACT(A57,""\d+""))), DATEVALUE(K57) - IF(RIGHT(A57,1)=""h"", VALUE(REGEXEXTRACT(A57,""\d+""))/24, IF(RIGHT(A57,1)=""d"", VALUE(REGEXEXTRACT(A57,""\d+"")), IF(RI"&"GHT(A57,1)=""w"", VALUE(REGEXEXTRACT(A57,""\d+""))*7, 0))) ) , ""YYYY-M-D"")"),"2026-2-16") -> 2026-2-16
A58: 3w | B58: Data Analyst | C58: Budapest or Pécs | D58: Hybrid | E58: Full Time | F58: Harman | G58: Harman: Manufactures audio equipment and infotainment systems for global markets | H58: 3+ YOE3+ years in data warehousing, analytics, and business analysis; proficient with BI tools (Qlik Sense, Power BI, Tableau). | I58: Power BI, Qlik Sense, Snowflake, Tableau, OBIEE | J58: Job Posting | K58: 46083 | L58: Departments - Data and Analytics, Budapest (Remote, Hybrid, Onsite), No keyword search, 6 months | M58: =IFERROR(__xludf.DUMMYFUNCTION("TEXT( IF(RIGHT(A58,2)=""mo"", EDATE(DATEVALUE(K58), -VALUE(REGEXEXTRACT(A58,""\d+""))), DATEVALUE(K58) - IF(RIGHT(A58,1)=""h"", VALUE(REGEXEXTRACT(A58,""\d+""))/24, IF(RIGHT(A58,1)=""d"", VALUE(REGEXEXTRACT(A58,""\d+"")), IF(RI"&"GHT(A58,1)=""w"", VALUE(REGEXEXTRACT(A58,""\d+""))*7, 0))) ) , ""YYYY-M-D"")"),"2026-2-9") -> 2026-2-9
A59: 3w | B59: Staff Product Analytics Engineer | C59: North America or Europe | D59: Remote | E59: Full Time | F59: Runway | G59: Runway: Develops generative AI tools for video and image production. | H59: 4+ YOE4+ years with data analytics/engineering, SQL/ETL/Python, cross-functional collaboration, data privacy, and tooling experience. | I59: SQL, ETL, Python, Data modeling | J59: Job Posting | K59: 46083 | L59: Departments - Data and Analytics, Budapest (Remote, Hybrid, Onsite), No keyword search, 6 months | M59: =IFERROR(__xludf.DUMMYFUNCTION("TEXT( IF(RIGHT(A59,2)=""mo"", EDATE(DATEVALUE(K59), -VALUE(REGEXEXTRACT(A59,""\d+""))), DATEVALUE(K59) - IF(RIGHT(A59,1)=""h"", VALUE(REGEXEXTRACT(A59,""\d+""))/24, IF(RIGHT(A59,1)=""d"", VALUE(REGEXEXTRACT(A59,""\d+"")), IF(RI"&"GHT(A59,1)=""w"", VALUE(REGEXEXTRACT(A59,""\d+""))*7, 0))) ) , ""YYYY-M-D"")"),"2026-2-9") -> 2026-2-9
A60: 3w | B60: Marketing Campaign Analytics Expert (fixed term) (Budapest, HU, 1112) | C60: Budapest, Budapest, Hungary | D60: Hybrid | E60: Full Time | F60: 4iG | G60: 4iGBudapest Stock Exchange: 4IG: Provides integrated telecommunications and information technology services. | H60: 1+ YOE1-3 years marketing or campaign management experience; bachelor's degree; English proficiency; telecom industry knowledge; SQL skills; familiar with Jira and Confluence. | I60: SQL, Jira, Confluence, Pega | J60: Job Posting | K60: 46083 | L60: Departments - Data and Analytics, Budapest (Remote, Hybrid, Onsite), No keyword search, 6 months | M60: =IFERROR(__xludf.DUMMYFUNCTION("TEXT( IF(RIGHT(A60,2)=""mo"", EDATE(DATEVALUE(K60), -VALUE(REGEXEXTRACT(A60,""\d+""))), DATEVALUE(K60) - IF(RIGHT(A60,1)=""h"", VALUE(REGEXEXTRACT(A60,""\d+""))/24, IF(RIGHT(A60,1)=""d"", VALUE(REGEXEXTRACT(A60,""\d+"")), IF(RI"&"GHT(A60,1)=""w"", VALUE(REGEXEXTRACT(A60,""\d+""))*7, 0))) ) , ""YYYY-M-D"")"),"2026-2-9") -> 2026-2-9
A61: 3w | B61: Adatbázis fejlesztő (Budapest, HU) | C61: Budapest, Budapest, Hungary | D61: Onsite | E61: Full Time | F61: Intesa Sanpaolo | G61: Intesa SanpaoloBIT: ISP: Provides comprehensive banking and financial services to international clients. | H61: Experience with Oracle PLSQL; data analysis, reporting, and data warehouse support; strong IT skills and problem solving. | I61: Oracle PLSQL, SQL, SAS, VBA | J61: Job Posting | K61: 46083 | L61: Departments - Data and Analytics, Budapest (Remote, Hybrid, Onsite), No keyword search, 6 months | M61: =IFERROR(__xludf.DUMMYFUNCTION("TEXT( IF(RIGHT(A61,2)=""mo"", EDATE(DATEVALUE(K61), -VALUE(REGEXEXTRACT(A61,""\d+""))), DATEVALUE(K61) - IF(RIGHT(A61,1)=""h"", VALUE(REGEXEXTRACT(A61,""\d+""))/24, IF(RIGHT(A61,1)=""d"", VALUE(REGEXEXTRACT(A61,""\d+"")), IF(RI"&"GHT(A61,1)=""w"", VALUE(REGEXEXTRACT(A61,""\d+""))*7, 0))) ) , ""YYYY-M-D"")"),"2026-2-9") -> 2026-2-9
A62: 3w | B62: Senior Marketing Analyst (AI & Web3) | C62: Europe | D62: Remote | E62: Full Time | F62: Somnia | G62: Somnia: High-performance Layer 1 blockchain for decentralized consumer applications. | H62: 4+ YOE4+ years in data analytics within DeFi/L1/L2; strong SQL; marketing attribution; web analytics; on-chain data experience; proficiency with analytics and visualization tools; experience with Agentic AI and on-chain data interpretation. | I62: SQL, GTM (Server-Side), GA4, Tableau, Power BI, Looker, Kaito, Python, R, NumPy, Pandas | J62: Job Posting | K62: 46083 | L62: Departments - Data and Analytics, Budapest (Remote, Hybrid, Onsite), No keyword search, 6 months | M62: =IFERROR(__xludf.DUMMYFUNCTION("TEXT( IF(RIGHT(A62,2)=""mo"", EDATE(DATEVALUE(K62), -VALUE(REGEXEXTRACT(A62,""\d+""))), DATEVALUE(K62) - IF(RIGHT(A62,1)=""h"", VALUE(REGEXEXTRACT(A62,""\d+""))/24, IF(RIGHT(A62,1)=""d"", VALUE(REGEXEXTRACT(A62,""\d+"")), IF(RI"&"GHT(A62,1)=""w"", VALUE(REGEXEXTRACT(A62,""\d+""))*7, 0))) ) , ""YYYY-M-D"")"),"2026-2-9") -> 2026-2-9
A63: 3w | B63: MDG Analyst (Budapest, HU) | C63: Budapest, Budapest, Hungary | D63: Onsite | E63: Contract | F63: Paramount Skydance | G63: Paramount SkydanceNASDAQ: PSKY: Produces and distributes films and television content globally. | H63: 0+ YOEBachelor's in Finance/Accounting/IT; 0-2 years data management/finance; ERP knowledge a plus; strong Excel; fluent English. | I63: SAP, Oracle, Excel | J63: Job Posting | K63: 46083 | L63: Departments - Data and Analytics, Budapest (Remote, Hybrid, Onsite), No keyword search, 6 months | M63: =IFERROR(__xludf.DUMMYFUNCTION("TEXT( IF(RIGHT(A63,2)=""mo"", EDATE(DATEVALUE(K63), -VALUE(REGEXEXTRACT(A63,""\d+""))), DATEVALUE(K63) - IF(RIGHT(A63,1)=""h"", VALUE(REGEXEXTRACT(A63,""\d+""))/24, IF(RIGHT(A63,1)=""d"", VALUE(REGEXEXTRACT(A63,""\d+"")), IF(RI"&"GHT(A63,1)=""w"", VALUE(REGEXEXTRACT(A63,""\d+""))*7, 0))) ) , ""YYYY-M-D"")"),"2026-2-9") -> 2026-2-9
A64: 3w | B64: EMEA Wealth Client Data Analyst | C64: Budapest, Budapest, Hungary | D64: Hybrid | E64: Full Time | F64: BlackRock | G64: BlackRockNYSE: BLK: Provides investment management, risk analytics, and advisory services globally. | H64: 1+ YOE1+ year in data/analytics or similar; basic SQL; English; CRM (Microsoft Dynamics) experience preferred; financial services experience a plus. | I64: SQL, Python, CRM (Microsoft Dynamics) | J64: Job Posting | K64: 46083 | L64: Departments - Data and Analytics, Budapest (Remote, Hybrid, Onsite), No keyword search, 6 months | M64: =IFERROR(__xludf.DUMMYFUNCTION("TEXT( IF(RIGHT(A64,2)=""mo"", EDATE(DATEVALUE(K64), -VALUE(REGEXEXTRACT(A64,""\d+""))), DATEVALUE(K64) - IF(RIGHT(A64,1)=""h"", VALUE(REGEXEXTRACT(A64,""\d+""))/24, IF(RIGHT(A64,1)=""d"", VALUE(REGEXEXTRACT(A64,""\d+"")), IF(RI"&"GHT(A64,1)=""w"", VALUE(REGEXEXTRACT(A64,""\d+""))*7, 0))) ) , ""YYYY-M-D"")"),"2026-2-9") -> 2026-2-9
A65: 3w | B65: Szakmai gyakorlat logisztikai területre (Budapest, HU) | C65: Budapest, Budapest, Hungary | D65: Onsite | E65: Internship | F65: Gedeon Richter | G65: Gedeon RichterBudapest Stock Exchange: RICHTER: Develops, manufactures, and distributes global pharmaceutical and biotechnology medicines. | H65: Active full-time student in higher education; strong communication; teamwork; proactive; MS Office. | I65: Power Query, Power BI, MS Office | J65: Job Posting | K65: 46083 | L65: Departments - Data and Analytics, Budapest (Remote, Hybrid, Onsite), No keyword search, 6 months | M65: =IFERROR(__xludf.DUMMYFUNCTION("TEXT( IF(RIGHT(A65,2)=""mo"", EDATE(DATEVALUE(K65), -VALUE(REGEXEXTRACT(A65,""\d+""))), DATEVALUE(K65) - IF(RIGHT(A65,1)=""h"", VALUE(REGEXEXTRACT(A65,""\d+""))/24, IF(RIGHT(A65,1)=""d"", VALUE(REGEXEXTRACT(A65,""\d+"")), IF(RI"&"GHT(A65,1)=""w"", VALUE(REGEXEXTRACT(A65,""\d+""))*7, 0))) ) , ""YYYY-M-D"")"),"2026-2-9") -> 2026-2-9
A66: 3w | B66: Master Data and Product Specialist (Budapest, HU) | C66: Budapest, Budapest, Hungary | D66: Hybrid | E66: Full Time | F66: Vodafone | G66: VodafoneLondon Stock Exchange: VOD: Provides telecommunications and digital services to consumers and businesses. | H66: 2+ YOE2-3 years in data governance/MDM, data quality management, automation, analytics; experience with SAP/Oracle planning interfaces; strong Excel/Power BI; stakeholder collaboration with planning teams and OEMs. | I66: SAP, SAP APO, SAP IBP, Oracle, ERP-to-planning-system interfaces, Power BI, Advanced Excel | J66: Job Posting | K66: 46083 | L66: Departments - Data and Analytics, Budapest (Remote, Hybrid, Onsite), No keyword search, 6 months | M66: =IFERROR(__xludf.DUMMYFUNCTION("TEXT( IF(RIGHT(A66,2)=""mo"", EDATE(DATEVALUE(K66), -VALUE(REGEXEXTRACT(A66,""\d+""))), DATEVALUE(K66) - IF(RIGHT(A66,1)=""h"", VALUE(REGEXEXTRACT(A66,""\d+""))/24, IF(RIGHT(A66,1)=""d"", VALUE(REGEXEXTRACT(A66,""\d+"")), IF(RI"&"GHT(A66,1)=""w"", VALUE(REGEXEXTRACT(A66,""\d+""))*7, 0))) ) , ""YYYY-M-D"")"),"2026-2-9") -> 2026-2-9
A67: 3w | B67: Senior Data Platform Engineer | C67: Europe | D67: Remote | E67: Full Time | F67: Playson | G67: Playson: Develops digital slot games and software for online casinos. | H67: 5+ YOE5+ years in data or backend engineering on production systems; experience with columnar databases, streaming systems, SQL and a programming language; focus on reliability and failure modes. | I67: ClickHouse, Snowflake, BigQuery, Kafka, Pub/Sub, CDC, Python, Java, Scala | J67: Job Posting | K67: 46083 | L67: Departments - Data and Analytics, Budapest (Remote, Hybrid, Onsite), No keyword search, 6 months | M67: =IFERROR(__xludf.DUMMYFUNCTION("TEXT( IF(RIGHT(A67,2)=""mo"", EDATE(DATEVALUE(K67), -VALUE(REGEXEXTRACT(A67,""\d+""))), DATEVALUE(K67) - IF(RIGHT(A67,1)=""h"", VALUE(REGEXEXTRACT(A67,""\d+""))/24, IF(RIGHT(A67,1)=""d"", VALUE(REGEXEXTRACT(A67,""\d+"")), IF(RI"&"GHT(A67,1)=""w"", VALUE(REGEXEXTRACT(A67,""\d+""))*7, 0))) ) , ""YYYY-M-D"")"),"2026-2-9") -> 2026-2-9
A68: 4w | B68: Risk Operations, Specialist Payment Risk | C68: Budapest, Budapest, Hungary | D68: Hybrid | E68: Full Time | F68: OKX | G68: OKX: Operates a global cryptocurrency exchange and decentralized Web3 wallet. | H68: 2+ YOEFraud/risk operations experience; at least 2 years in fraud investigation; crypto/fintech risk focus; strong English; available for 24x7 shift; good communication. | I68: Chainalysis, Blockchain analytics tools | J68: Job Posting | K68: 46083 | L68: Departments - Data and Analytics, Budapest (Remote, Hybrid, Onsite), No keyword search, 6 months | M68: =IFERROR(__xludf.DUMMYFUNCTION("TEXT( IF(RIGHT(A68,2)=""mo"", EDATE(DATEVALUE(K68), -VALUE(REGEXEXTRACT(A68,""\d+""))), DATEVALUE(K68) - IF(RIGHT(A68,1)=""h"", VALUE(REGEXEXTRACT(A68,""\d+""))/24, IF(RIGHT(A68,1)=""d"", VALUE(REGEXEXTRACT(A68,""\d+"")), IF(RI"&"GHT(A68,1)=""w"", VALUE(REGEXEXTRACT(A68,""\d+""))*7, 0))) ) , ""YYYY-M-D"")"),"2026-2-2") -> 2026-2-2
A69: 4w | B69: Data Engineer | C69: Budapest, Budapest, Hungary | D69: Onsite | E69: Full Time | F69: Qneiform | G69: Qneiform: Provides an AI-driven talent intelligence platform for recruitment. | H69: Experience in data engineering and constructing data pipelines. Strong SQL and Python skills. | I69: Not available | J69: Job Posting | K69: 46083 | L69: Departments - Data and Analytics, Budapest (Remote, Hybrid, Onsite), No keyword search, 6 months | M69: =IFERROR(__xludf.DUMMYFUNCTION("TEXT( IF(RIGHT(A69,2)=""mo"", EDATE(DATEVALUE(K69), -VALUE(REGEXEXTRACT(A69,""\d+""))), DATEVALUE(K69) - IF(RIGHT(A69,1)=""h"", VALUE(REGEXEXTRACT(A69,""\d+""))/24, IF(RIGHT(A69,1)=""d"", VALUE(REGEXEXTRACT(A69,""\d+"")), IF(RI"&"GHT(A69,1)=""w"", VALUE(REGEXEXTRACT(A69,""\d+""))*7, 0))) ) , ""YYYY-M-D"")"),"2026-2-2") -> 2026-2-2
A70: 1mo | B70: Tableau Frontend BI Professional | C70: Budapest, Budapest, Hungary | D70: Hybrid | E70: Full Time | F70: INNIO | G70: INNIO: Manufactures gas engines and distributed power generation systems. | H70: 2+ YOE2-5 years Tableau experience; solid SQL; strong communication. | I70: Tableau, SQL, Databricks, Python (nice-to-have) | J70: Job Posting | K70: 46083 | L70: Departments - Data and Analytics, Budapest (Remote, Hybrid, Onsite), No keyword search, 6 months | M70: =IFERROR(__xludf.DUMMYFUNCTION("TEXT( IF(RIGHT(A70,2)=""mo"", EDATE(DATEVALUE(K70), -VALUE(REGEXEXTRACT(A70,""\d+""))), DATEVALUE(K70) - IF(RIGHT(A70,1)=""h"", VALUE(REGEXEXTRACT(A70,""\d+""))/24, IF(RIGHT(A70,1)=""d"", VALUE(REGEXEXTRACT(A70,""\d+"")), IF(RI"&"GHT(A70,1)=""w"", VALUE(REGEXEXTRACT(A70,""\d+""))*7, 0))) ) , ""YYYY-M-D"")"),"2026-2-2") -> 2026-2-2
A71: 1mo | B71: BI Full Stack Developer | C71: Budapest, Budapest, Hungary | D71: Hybrid | E71: Full Time | F71: INNIO | G71: INNIO: Manufactures gas engines and decentralized energy systems. | H71: Strong backend BI foundation; SQL expert; Databricks data validation; Python automation; backend-to-frontend BI enablement. | I71: SQL, Databricks, Python, dbt, Dagster | J71: Job Posting | K71: 46083 | L71: Departments - Data and Analytics, Budapest (Remote, Hybrid, Onsite), No keyword search, 6 months | M71: =IFERROR(__xludf.DUMMYFUNCTION("TEXT( IF(RIGHT(A71,2)=""mo"", EDATE(DATEVALUE(K71), -VALUE(REGEXEXTRACT(A71,""\d+""))), DATEVALUE(K71) - IF(RIGHT(A71,1)=""h"", VALUE(REGEXEXTRACT(A71,""\d+""))/24, IF(RIGHT(A71,1)=""d"", VALUE(REGEXEXTRACT(A71,""\d+"")), IF(RI"&"GHT(A71,1)=""w"", VALUE(REGEXEXTRACT(A71,""\d+""))*7, 0))) ) , ""YYYY-M-D"")"),"2026-2-2") -> 2026-2-2
A72: 1mo | B72: Data Analytics Analyst | C72: Budapest or Debrecen | D72: Hybrid | E72: Full Time | F72: Emerson | G72: EmersonNYSE: EMR: Provides industrial automation equipment and engineering software solutions. | H72: 2+ YOE2+ years in analytics, reporting, and data transformation; strong SQL; experience with BI tools; ability to deliver dashboards and insights. | I72: SQL, PowerBI, Tableau, Qubole, Snowflake, DBT, Python, R | J72: Job Posting | K72: 46083 | L72: Departments - Data and Analytics, Budapest (Remote, Hybrid, Onsite), No keyword search, 6 months | M72: =IFERROR(__xludf.DUMMYFUNCTION("TEXT( IF(RIGHT(A72,2)=""mo"", EDATE(DATEVALUE(K72), -VALUE(REGEXEXTRACT(A72,""\d+""))), DATEVALUE(K72) - IF(RIGHT(A72,1)=""h"", VALUE(REGEXEXTRACT(A72,""\d+""))/24, IF(RIGHT(A72,1)=""d"", VALUE(REGEXEXTRACT(A72,""\d+"")), IF(RI"&"GHT(A72,1)=""w"", VALUE(REGEXEXTRACT(A72,""\d+""))*7, 0))) ) , ""YYYY-M-D"")"),"2026-2-2") -> 2026-2-2
A73: 1mo | B73: Data Scientist | C73: Budapest, Budapest, Hungary | D73: Hybrid | E73: Full Time | F73: TAKKT | G73: TAKKTXETRA: TTK: B2B omnichannel distributor of business equipment and warehouse supplies | H73: Degree in Computer Science, Data Science, Mathematics, Physics, or related field; strong Python or R; ML frameworks; experience with LLMs and generative AI; knowledge of cloud; production deployment experience. | I73: Python, R, Pandas, Scikit-learn, PyTorch, TensorFlow, OpenAI, Hugging Face, Azure, AWS, GCP | J73: Job Posting | K73: 46083 | L73: Departments - Data and Analytics, Budapest (Remote, Hybrid, Onsite), No keyword search, 6 months | M73: =IFERROR(__xludf.DUMMYFUNCTION("TEXT( IF(RIGHT(A73,2)=""mo"", EDATE(DATEVALUE(K73), -VALUE(REGEXEXTRACT(A73,""\d+""))), DATEVALUE(K73) - IF(RIGHT(A73,1)=""h"", VALUE(REGEXEXTRACT(A73,""\d+""))/24, IF(RIGHT(A73,1)=""d"", VALUE(REGEXEXTRACT(A73,""\d+"")), IF(RI"&"GHT(A73,1)=""w"", VALUE(REGEXEXTRACT(A73,""\d+""))*7, 0))) ) , ""YYYY-M-D"")"),"2026-2-2") -> 2026-2-2
A74: 1mo | B74: Monetization Analyst - Leaply | C74: Spain or Lithuania or Poland or Ukraine or Europe | D74: Remote | E74: Full Time | F74: Skelar | G74: Skelar: Creates and scales international technology businesses across multiple niches. | H74: 2+ YOE2+ years in data or operations analytics; strong SQL; Tableau; Amplitude; interest in AI/automation. | I74: BigQuery, Tableau, Amplitude, AI/ML Tools | J74: Job Posting | K74: 46083 | L74: Departments - Data and Analytics, Budapest (Remote, Hybrid, Onsite), No keyword search, 6 months | M74: =IFERROR(__xludf.DUMMYFUNCTION("TEXT( IF(RIGHT(A74,2)=""mo"", EDATE(DATEVALUE(K74), -VALUE(REGEXEXTRACT(A74,""\d+""))), DATEVALUE(K74) - IF(RIGHT(A74,1)=""h"", VALUE(REGEXEXTRACT(A74,""\d+""))/24, IF(RIGHT(A74,1)=""d"", VALUE(REGEXEXTRACT(A74,""\d+"")), IF(RI"&"GHT(A74,1)=""w"", VALUE(REGEXEXTRACT(A74,""\d+""))*7, 0))) ) , ""YYYY-M-D"")"),"2026-2-2") -> 2026-2-2
A75: 1mo | B75: Senior Analytics Engineer | C75: North America or Europe | D75: Remote | E75: Full Time | F75: PandaDoc | G75: PandaDoc: All-in-one document workflow automation and electronic signature platform. | H75: 5+ YOE5+ years in analytics engineering or data engineering; expert SQL; strong dbt; Snowflake or similar warehouse; Python; data governance; SaaS metrics knowledge. | I75: Snowflake, dbt, Salesforce, HubSpot, Recurly, Select Star, Monte Carlo, Hightouch, PostHog, Python, SQL, Airflow | J75: Job Posting | K75: 46083 | L75: Departments - Data and Analytics, Budapest (Remote, Hybrid, Onsite), No keyword search, 6 months | M75: =IFERROR(__xludf.DUMMYFUNCTION("TEXT( IF(RIGHT(A75,2)=""mo"", EDATE(DATEVALUE(K75), -VALUE(REGEXEXTRACT(A75,""\d+""))), DATEVALUE(K75) - IF(RIGHT(A75,1)=""h"", VALUE(REGEXEXTRACT(A75,""\d+""))/24, IF(RIGHT(A75,1)=""d"", VALUE(REGEXEXTRACT(A75,""\d+"")), IF(RI"&"GHT(A75,1)=""w"", VALUE(REGEXEXTRACT(A75,""\d+""))*7, 0))) ) , ""YYYY-M-D"")"),"2026-2-2") -> 2026-2-2
A76: 1mo | B76: Product Analyst | C76: Europe or Asia | D76: Remote | E76: Full Time | F76: Nansen | G76: Nansen: Provides blockchain data analytics and market intelligence for investors. | H76: 3+ YOE3+ years in data analysis (product/growth/marketing); proficient in SQL and Python; crypto trading experience; AI tool experience; OKR familiarity; strong crypto markets knowledge. | I76: SQL, Python, dbt, Claude Code, Cursor | J76: Job Posting | K76: 46083 | L76: Departments - Data and Analytics, Budapest (Remote, Hybrid, Onsite), No keyword search, 6 months | M76: =IFERROR(__xludf.DUMMYFUNCTION("TEXT( IF(RIGHT(A76,2)=""mo"", EDATE(DATEVALUE(K76), -VALUE(REGEXEXTRACT(A76,""\d+""))), DATEVALUE(K76) - IF(RIGHT(A76,1)=""h"", VALUE(REGEXEXTRACT(A76,""\d+""))/24, IF(RIGHT(A76,1)=""d"", VALUE(REGEXEXTRACT(A76,""\d+"")), IF(RI"&"GHT(A76,1)=""w"", VALUE(REGEXEXTRACT(A76,""\d+""))*7, 0))) ) , ""YYYY-M-D"")"),"2026-2-2") -> 2026-2-2
A77: 1mo | B77: Catalog Quality Senior Specialist | C77: Budapest, Budapest, Hungary | D77: Onsite | E77: Full Time | F77: Wolt | G77: Wolt: Connecting consumers with local restaurants and retail merchants. | H77: 3+ YOE3+ years in catalog/content management or data QA; fluent in Hungarian and English; strong Excel/Google Sheets skills; ability to collaborate with stakeholders and vendors. | I77: Microsoft Excel, Google Sheets | J77: Job Posting | K77: 46083 | L77: Departments - Data and Analytics, Budapest (Remote, Hybrid, Onsite), No keyword search, 6 months | M77: =IFERROR(__xludf.DUMMYFUNCTION("TEXT( IF(RIGHT(A77,2)=""mo"", EDATE(DATEVALUE(K77), -VALUE(REGEXEXTRACT(A77,""\d+""))), DATEVALUE(K77) - IF(RIGHT(A77,1)=""h"", VALUE(REGEXEXTRACT(A77,""\d+""))/24, IF(RIGHT(A77,1)=""d"", VALUE(REGEXEXTRACT(A77,""\d+"")), IF(RI"&"GHT(A77,1)=""w"", VALUE(REGEXEXTRACT(A77,""\d+""))*7, 0))) ) , ""YYYY-M-D"")"),"2026-2-2") -> 2026-2-2
A78: 1mo | B78: Junior AI Prompt & Workflow Specialist | C78: Budapest, Budapest, Hungary | D78: Hybrid | E78: Full Time, Contract | F78: UniCredit | G78: UniCreditBorsa Italiana: UCG: Pan-European bank providing retail, corporate, and investment banking services. | H78: 2+ YOE1–3 years in digital, data, process improvement, business analysis, or tech-related fields; strong English; interest in AI and technology; daily use of generative AI tools; advanced prompt principles; ability to translate business problems into AI approaches; experience with large language models is a plus; strong communication with business users;... | I78: Copilot Chat, ChatGPT, Google Gemini | J78: Job Posting | K78: 46083 | L78: Departments - Data and Analytics, Budapest (Remote, Hybrid, Onsite), No keyword search, 6 months | M78: =IFERROR(__xludf.DUMMYFUNCTION("TEXT( IF(RIGHT(A78,2)=""mo"", EDATE(DATEVALUE(K78), -VALUE(REGEXEXTRACT(A78,""\d+""))), DATEVALUE(K78) - IF(RIGHT(A78,1)=""h"", VALUE(REGEXEXTRACT(A78,""\d+""))/24, IF(RIGHT(A78,1)=""d"", VALUE(REGEXEXTRACT(A78,""\d+"")), IF(RI"&"GHT(A78,1)=""w"", VALUE(REGEXEXTRACT(A78,""\d+""))*7, 0))) ) , ""YYYY-M-D"")"),"2026-2-2") -> 2026-2-2
A79: 1mo | B79: Data Scientist | C79: Latvia or Spain or Estonia or Europe | D79: Remote | E79: Full Time | F79: Bondora | G79: Bondora: European digital platform for consumer lending and P2P investing. | H79: Proven credit modeling experience; strong Python/SQL, ML libraries; production data pipelines; cloud (Azure); containerization (Docker/Kubernetes); data visualization (Tableau). | I79: Python, SQL, scikit-learn, TensorFlow, PyTorch, Azure, Docker, Kubernetes, Tableau | J79: Job Posting | K79: 46083 | L79: Departments - Data and Analytics, Budapest (Remote, Hybrid, Onsite), No keyword search, 6 months | M79: =IFERROR(__xludf.DUMMYFUNCTION("TEXT( IF(RIGHT(A79,2)=""mo"", EDATE(DATEVALUE(K79), -VALUE(REGEXEXTRACT(A79,""\d+""))), DATEVALUE(K79) - IF(RIGHT(A79,1)=""h"", VALUE(REGEXEXTRACT(A79,""\d+""))/24, IF(RIGHT(A79,1)=""d"", VALUE(REGEXEXTRACT(A79,""\d+"")), IF(RI"&"GHT(A79,1)=""w"", VALUE(REGEXEXTRACT(A79,""\d+""))*7, 0))) ) , ""YYYY-M-D"")"),"2026-2-2") -> 2026-2-2
A80: 1mo | B80: Marketing Data Engineer | C80: United States or India or Europe | D80: Remote | E80: Full Time | F80: LHH | G80: LHHSIX Swiss Exchange: ADEN: Global provider of talent development and career transition services. | H80: 4+ YOEDesigning data architecture, building data models, and delivering marketing analytics dashboards. | I80: SQL, Azure, dbt, Airflow, Fivetran, Stitch, GA4, Salesforce, Pardot, Marketing Cloud, Looker Studio, Power BI | J80: Job Posting | K80: 46083 | L80: Departments - Data and Analytics, Budapest (Remote, Hybrid, Onsite), No keyword search, 6 months | M80: =IFERROR(__xludf.DUMMYFUNCTION("TEXT( IF(RIGHT(A80,2)=""mo"", EDATE(DATEVALUE(K80), -VALUE(REGEXEXTRACT(A80,""\d+""))), DATEVALUE(K80) - IF(RIGHT(A80,1)=""h"", VALUE(REGEXEXTRACT(A80,""\d+""))/24, IF(RIGHT(A80,1)=""d"", VALUE(REGEXEXTRACT(A80,""\d+"")), IF(RI"&"GHT(A80,1)=""w"", VALUE(REGEXEXTRACT(A80,""\d+""))*7, 0))) ) , ""YYYY-M-D"")"),"2026-2-2") -> 2026-2-2
A81: 1mo | B81: Business Analyst | C81: Stare Miasto or Brno or Bucharest or Budapest | D81: Hybrid | E81: Full Time | F81: Kramp | G81: Kramp: Wholesaler of spare parts and accessories for agricultural machinery. | H81: 3+ YOEBachelor or Master in related field; 3-7 years analytics experience; fluent in English and Polish/Czech/Hungarian/Romanian; proficient in Tableau, SQL, or Power BI; strong stakeholder management and advisory skills. | I81: Tableau, SQL, Power BI | J81: Job Posting | K81: 46083 | L81: Departments - Data and Analytics, Budapest (Remote, Hybrid, Onsite), No keyword search, 6 months | M81: =IFERROR(__xludf.DUMMYFUNCTION("TEXT( IF(RIGHT(A81,2)=""mo"", EDATE(DATEVALUE(K81), -VALUE(REGEXEXTRACT(A81,""\d+""))), DATEVALUE(K81) - IF(RIGHT(A81,1)=""h"", VALUE(REGEXEXTRACT(A81,""\d+""))/24, IF(RIGHT(A81,1)=""d"", VALUE(REGEXEXTRACT(A81,""\d+"")), IF(RI"&"GHT(A81,1)=""w"", VALUE(REGEXEXTRACT(A81,""\d+""))*7, 0))) ) , ""YYYY-M-D"")"),"2026-2-2") -> 2026-2-2
A82: 1mo | B82: Commercial Analytics Business Analyst (fixed-term) | C82: Budapest, Budapest, Hungary | D82: Onsite | E82: Full Time | F82: Roche | G82: RocheSIX Swiss Exchange: ROG: Develops and manufactures innovative pharmaceuticals and diagnostic tests. | H82: Experience with Snowflake and Tableau; knowledge of ThoughtSpot and AI/ML; Agile/Scrum; strong communication in English. | I82: Snowflake, Tableau, ThoughtSpot, AI/ML frameworks, Scrum/Kanban | J82: Job Posting | K82: 46083 | L82: Departments - Data and Analytics, Budapest (Remote, Hybrid, Onsite), No keyword search, 6 months | M82: =IFERROR(__xludf.DUMMYFUNCTION("TEXT( IF(RIGHT(A82,2)=""mo"", EDATE(DATEVALUE(K82), -VALUE(REGEXEXTRACT(A82,""\d+""))), DATEVALUE(K82) - IF(RIGHT(A82,1)=""h"", VALUE(REGEXEXTRACT(A82,""\d+""))/24, IF(RIGHT(A82,1)=""d"", VALUE(REGEXEXTRACT(A82,""\d+"")), IF(RI"&"GHT(A82,1)=""w"", VALUE(REGEXEXTRACT(A82,""\d+""))*7, 0))) ) , ""YYYY-M-D"")"),"2026-2-2") -> 2026-2-2
A83: 1mo | B83: Database Engineer (Independent Contractor) | C83: Poland or Hungary or Ukraine | D83: Remote | E83: Full Time, Contract | F83: Jabil | G83: JabilNYSE: JBL: Provides design, engineering, and manufacturing services for global brands. | H83: ETL/ELT experience with cloud data platforms; strong SQL; experience with data modeling and CI/CD; independent contractor role. | I83: Azure, Databricks, Spark, ClickHouse, Airflow, dbt, Kafka, Event Hubs, Delta Lake, Synapse, Data Factory, Snowflake, BigQuery, Redshift, Python | J83: Job Posting | K83: 46083 | L83: Departments - Data and Analytics, Budapest (Remote, Hybrid, Onsite), No keyword search, 6 months | M83: =IFERROR(__xludf.DUMMYFUNCTION("TEXT( IF(RIGHT(A83,2)=""mo"", EDATE(DATEVALUE(K83), -VALUE(REGEXEXTRACT(A83,""\d+""))), DATEVALUE(K83) - IF(RIGHT(A83,1)=""h"", VALUE(REGEXEXTRACT(A83,""\d+""))/24, IF(RIGHT(A83,1)=""d"", VALUE(REGEXEXTRACT(A83,""\d+"")), IF(RI"&"GHT(A83,1)=""w"", VALUE(REGEXEXTRACT(A83,""\d+""))*7, 0))) ) , ""YYYY-M-D"")"),"2026-2-2") -> 2026-2-2
A84: 1mo | B84: Data Analyst I | C84: Europe | D84: Remote | E84: Full Time | F84: Parker | G84: Parker: Provides virtual corporate cards and financial software for eCommerce businesses. | H84: Proficient in SQL; Python for data workflows; strong data modeling; ability to translate questions into metrics; AI-first analytics mindset; ownership mindset; strong business judgment and clarity. | I84: SQL, Python | J84: Job Posting | K84: 46083 | L84: Departments - Data and Analytics, Budapest (Remote, Hybrid, Onsite), No keyword search, 6 months | M84: =IFERROR(__xludf.DUMMYFUNCTION("TEXT( IF(RIGHT(A84,2)=""mo"", EDATE(DATEVALUE(K84), -VALUE(REGEXEXTRACT(A84,""\d+""))), DATEVALUE(K84) - IF(RIGHT(A84,1)=""h"", VALUE(REGEXEXTRACT(A84,""\d+""))/24, IF(RIGHT(A84,1)=""d"", VALUE(REGEXEXTRACT(A84,""\d+"")), IF(RI"&"GHT(A84,1)=""w"", VALUE(REGEXEXTRACT(A84,""\d+""))*7, 0))) ) , ""YYYY-M-D"")"),"2026-2-2") -> 2026-2-2
A85: 1mo | B85: Quality Review & Reporting Analyst | C85: Budapest, Budapest, Hungary | D85: Hybrid | E85: Full Time | F85: Cushman & Wakefield | G85: Cushman & WakefieldNYSE: CWK: Provides commercial real estate and property management services globally. | H85: Bachelor's or master's degree required; no prior experience; English intermediate; strong IT, MS Office; analytical and communicative; team-oriented and proactive. | I85: Microsoft Office, IT tools | J85: Job Posting | K85: 46083 | L85: Departments - Data and Analytics, Budapest (Remote, Hybrid, Onsite), No keyword search, 6 months | M85: =IFERROR(__xludf.DUMMYFUNCTION("TEXT( IF(RIGHT(A85,2)=""mo"", EDATE(DATEVALUE(K85), -VALUE(REGEXEXTRACT(A85,""\d+""))), DATEVALUE(K85) - IF(RIGHT(A85,1)=""h"", VALUE(REGEXEXTRACT(A85,""\d+""))/24, IF(RIGHT(A85,1)=""d"", VALUE(REGEXEXTRACT(A85,""\d+"")), IF(RI"&"GHT(A85,1)=""w"", VALUE(REGEXEXTRACT(A85,""\d+""))*7, 0))) ) , ""YYYY-M-D"")"),"2026-2-2") -> 2026-2-2
A86: 1mo | B86: CEE Customer Performance Lead | C86: Budapest or Bucharest or Praha or Warsaw or Kiev | D86: Hybrid | E86: Full Time | F86: Opella | G86: Opella: Manufactures and sells over-the-counter medicines and health supplements. | H86: 5+ YOEMinimum 5 years’ experience in Revenue Management in pharma; degree in econometrics, economics or engineering; highly collaborative; strong analytical thinking; advanced Excel; fluent in English; experience leading multi-market teams. | I86: Excel | J86: Job Posting | K86: 46083 | L86: Departments - Data and Analytics, Budapest (Remote, Hybrid, Onsite), No keyword search, 6 months | M86: =IFERROR(__xludf.DUMMYFUNCTION("TEXT( IF(RIGHT(A86,2)=""mo"", EDATE(DATEVALUE(K86), -VALUE(REGEXEXTRACT(A86,""\d+""))), DATEVALUE(K86) - IF(RIGHT(A86,1)=""h"", VALUE(REGEXEXTRACT(A86,""\d+""))/24, IF(RIGHT(A86,1)=""d"", VALUE(REGEXEXTRACT(A86,""\d+"")), IF(RI"&"GHT(A86,1)=""w"", VALUE(REGEXEXTRACT(A86,""\d+""))*7, 0))) ) , ""YYYY-M-D"")"),"2026-2-2") -> 2026-2-2
A87: 1mo | B87: SAP Business Data Cloud Consultant, Data & Analytics (Budapest, HU, 1031) | C87: Budapest, Budapest, Hungary | D87: Hybrid | E87: Full Time | F87: SAP | G87: SAPFrankfurt Stock Exchange: SAP: Provides enterprise software for business operations and data management. | H87: 2+ YOEMaster’s degree preferred; strong analytical skills; English C1; SAP BW/4HANA data/analytics expertise; 2+ years SAP analytics experience; SAP certifications. | I87: SAP BW/4HANA, SAP Datasphere, SAP Data Service, SAP Data Intelligence, SAP Analytics Cloud, SAP Business Data Cloud (BDC), SAP Business Technology Platform (BTP) | J87: Job Posting | K87: 46083 | L87: Departments - Data and Analytics, Budapest (Remote, Hybrid, Onsite), No keyword search, 6 months | M87: =IFERROR(__xludf.DUMMYFUNCTION("TEXT( IF(RIGHT(A87,2)=""mo"", EDATE(DATEVALUE(K87), -VALUE(REGEXEXTRACT(A87,""\d+""))), DATEVALUE(K87) - IF(RIGHT(A87,1)=""h"", VALUE(REGEXEXTRACT(A87,""\d+""))/24, IF(RIGHT(A87,1)=""d"", VALUE(REGEXEXTRACT(A87,""\d+"")), IF(RI"&"GHT(A87,1)=""w"", VALUE(REGEXEXTRACT(A87,""\d+""))*7, 0))) ) , ""YYYY-M-D"")"),"2026-2-2") -> 2026-2-2
A88: 1mo | B88: AI Engineer | C88: Austria or Europe | D88: Remote | E88: Full Time | F88: Platomics | G88: Platomics: Automating regulatory compliance for in vitro diagnostic manufacturers and laboratories. | H88: 7+ YOE7+ years AI/ML engineering or data science; 5+ years deploying production AI/ML systems; NLP/ document processing/ unstructured data; ML/LLM systems; regulated domains; strong Python; cloud experience (AWS/Azure/GCP). | I88: Python, ML Frameworks, NLP, Document Processing, Computer Vision, Unstructured Data, MLOps, Monitoring, Deployment, AWS, Azure, GCP | J88: Job Posting | K88: 46083 | L88: Departments - Data and Analytics, Budapest (Remote, Hybrid, Onsite), No keyword search, 6 months | M88: =IFERROR(__xludf.DUMMYFUNCTION("TEXT( IF(RIGHT(A88,2)=""mo"", EDATE(DATEVALUE(K88), -VALUE(REGEXEXTRACT(A88,""\d+""))), DATEVALUE(K88) - IF(RIGHT(A88,1)=""h"", VALUE(REGEXEXTRACT(A88,""\d+""))/24, IF(RIGHT(A88,1)=""d"", VALUE(REGEXEXTRACT(A88,""\d+"")), IF(RI"&"GHT(A88,1)=""w"", VALUE(REGEXEXTRACT(A88,""\d+""))*7, 0))) ) , ""YYYY-M-D"")"),"2026-2-2") -> 2026-2-2
A89: 1mo | B89: Szolgáltatás fejlesztési szakértő (Budapest, HU, 1087) | C89: Budapest, Budapest, Hungary | D89: Hybrid | E89: Full Time | F89: Allianz | G89: AllianzFrankfurt Stock Exchange: ALV: Provides global insurance, asset management, and assistance services. | H89: 2+ YOEHigher education required; 2-3 years in complex process development; strong communication; analytical; interest in anti-fraud; knowledge of AI tools. | I89: AI tools, Data analysis tools, Automation systems | J89: Job Posting | K89: 46083 | L89: Departments - Data and Analytics, Budapest (Remote, Hybrid, Onsite), No keyword search, 6 months | M89: =IFERROR(__xludf.DUMMYFUNCTION("TEXT( IF(RIGHT(A89,2)=""mo"", EDATE(DATEVALUE(K89), -VALUE(REGEXEXTRACT(A89,""\d+""))), DATEVALUE(K89) - IF(RIGHT(A89,1)=""h"", VALUE(REGEXEXTRACT(A89,""\d+""))/24, IF(RIGHT(A89,1)=""d"", VALUE(REGEXEXTRACT(A89,""\d+"")), IF(RI"&"GHT(A89,1)=""w"", VALUE(REGEXEXTRACT(A89,""\d+""))*7, 0))) ) , ""YYYY-M-D"")"),"2026-2-2") -> 2026-2-2
A90: 1mo | B90: Senior Database Engineer (AWS/PostgreSQL) | C90: Europe or Croatia | D90: Remote | E90: Contract | F90: BB Agency | G90: BB Agency: Strategic digital agency specializing in branding and product design. | H90: 5+ YOE5+ years in database engineering; SaaS multi-tenant architecture; PostgreSQL internals; Oracle-to-Postgres migration; AWS Aurora PostgreSQL and QLDB experience; English communication; remote work in Europe/LATAM. | I90: Amazon Aurora PostgreSQL, Amazon QLDB, Oracle PL/SQL, PostgreSQL, AWS CDK, TypeScript, Java | J90: Job Posting | K90: 46083 | L90: Departments - Data and Analytics, Budapest (Remote, Hybrid, Onsite), No keyword search, 6 months | M90: =IFERROR(__xludf.DUMMYFUNCTION("TEXT( IF(RIGHT(A90,2)=""mo"", EDATE(DATEVALUE(K90), -VALUE(REGEXEXTRACT(A90,""\d+""))), DATEVALUE(K90) - IF(RIGHT(A90,1)=""h"", VALUE(REGEXEXTRACT(A90,""\d+""))/24, IF(RIGHT(A90,1)=""d"", VALUE(REGEXEXTRACT(A90,""\d+"")), IF(RI"&"GHT(A90,1)=""w"", VALUE(REGEXEXTRACT(A90,""\d+""))*7, 0))) ) , ""YYYY-M-D"")"),"2026-2-2") -> 2026-2-2
A91: 1mo | B91: Safety & PV Specialist I (ICSR Processing + MedDRA Coding) - Hybrid Based | C91: Budapest, Budapest, Hungary | D91: Hybrid | E91: Full Time | F91: Syneos Health | G91: Syneos Health: Provides clinical and commercial services to biopharmaceutical companies. | H91: 0+ YOEPerform ICSR processing, MedDRA coding, data management, and safety reporting per GVP/GCP; hybrid, full-time. | I91: MedDRA, ICSR processing, data management, pharmacovigilance | J91: Job Posting | K91: 46083 | L91: Departments - Data and Analytics, Budapest (Remote, Hybrid, Onsite), No keyword search, 6 months | M91: =IFERROR(__xludf.DUMMYFUNCTION("TEXT( IF(RIGHT(A91,2)=""mo"", EDATE(DATEVALUE(K91), -VALUE(REGEXEXTRACT(A91,""\d+""))), DATEVALUE(K91) - IF(RIGHT(A91,1)=""h"", VALUE(REGEXEXTRACT(A91,""\d+""))/24, IF(RIGHT(A91,1)=""d"", VALUE(REGEXEXTRACT(A91,""\d+"")), IF(RI"&"GHT(A91,1)=""w"", VALUE(REGEXEXTRACT(A91,""\d+""))*7, 0))) ) , ""YYYY-M-D"")"),"2026-2-2") -> 2026-2-2
A92: 1mo | B92: Data Engineer | C92: Europe | D92: Remote | E92: Full Time | F92: Deel | G92: Deel: Global payroll and HR platform for international teams. | H92: 3+ YOE3+ years data engineering experience; strong SQL; Python; ETL tooling; data modeling; cross-functional collaboration. | I92: SQL, Python, Apache Airflow, Data Warehouse, ETL | J92: Job Posting | K92: 46083 | L92: Departments - Data and Analytics, Budapest (Remote, Hybrid, Onsite), No keyword search, 6 months | M92: =IFERROR(__xludf.DUMMYFUNCTION("TEXT( IF(RIGHT(A92,2)=""mo"", EDATE(DATEVALUE(K92), -VALUE(REGEXEXTRACT(A92,""\d+""))), DATEVALUE(K92) - IF(RIGHT(A92,1)=""h"", VALUE(REGEXEXTRACT(A92,""\d+""))/24, IF(RIGHT(A92,1)=""d"", VALUE(REGEXEXTRACT(A92,""\d+"")), IF(RI"&"GHT(A92,1)=""w"", VALUE(REGEXEXTRACT(A92,""\d+""))*7, 0))) ) , ""YYYY-M-D"")"),"2026-2-2") -> 2026-2-2
A93: 1mo | B93: Freelance Senior Data Analyst | C93: Sofia or Bulgaria or Macedonia or Poland or Portugal or Ukraine or XK | D93: Remote | E93: Contract | F93: Valtech | G93: Valtech: Global agency providing digital transformation and experience innovation services | H93: 5+ YOE5+ years with Adobe Analytics and Accutics; dashboard creation; CID links; client-facing; PowerPoint/Excel; strong analytical and communication skills; independent; willing to learn. | I93: Adobe Analytics, Accutics, PowerPoint, Excel | J93: Job Posting | K93: 46083 | L93: Departments - Data and Analytics, Budapest (Remote, Hybrid, Onsite), No keyword search, 6 months | M93: =IFERROR(__xludf.DUMMYFUNCTION("TEXT( IF(RIGHT(A93,2)=""mo"", EDATE(DATEVALUE(K93), -VALUE(REGEXEXTRACT(A93,""\d+""))), DATEVALUE(K93) - IF(RIGHT(A93,1)=""h"", VALUE(REGEXEXTRACT(A93,""\d+""))/24, IF(RIGHT(A93,1)=""d"", VALUE(REGEXEXTRACT(A93,""\d+"")), IF(RI"&"GHT(A93,1)=""w"", VALUE(REGEXEXTRACT(A93,""\d+""))*7, 0))) ) , ""YYYY-M-D"")"),"2026-2-2") -> 2026-2-2
A94: 1mo | B94: Senior Data Analyst | C94: Budapest, Budapest, Hungary | D94: Hybrid | E94: Full Time | F94: Zocks | G94: Zocks: AI platform automating administrative tasks for financial advisors. | H94: 4+ YOE4+ years in data analysis/BI, SQL proficiency, strong data visualization, experience with B2B IT products; excellent English and Hungarian; Bachelor’s in Data Science/Statistics/Computer Science/Business. | I94: SQL, Power BI, Tableau, Looker, AWS, Python, Excel | J94: Job Posting | K94: 46083 | L94: Departments - Data and Analytics, Budapest (Remote, Hybrid, Onsite), No keyword search, 6 months | M94: =IFERROR(__xludf.DUMMYFUNCTION("TEXT( IF(RIGHT(A94,2)=""mo"", EDATE(DATEVALUE(K94), -VALUE(REGEXEXTRACT(A94,""\d+""))), DATEVALUE(K94) - IF(RIGHT(A94,1)=""h"", VALUE(REGEXEXTRACT(A94,""\d+""))/24, IF(RIGHT(A94,1)=""d"", VALUE(REGEXEXTRACT(A94,""\d+"")), IF(RI"&"GHT(A94,1)=""w"", VALUE(REGEXEXTRACT(A94,""\d+""))*7, 0))) ) , ""YYYY-M-D"")"),"2026-2-2") -> 2026-2-2
A95: 1mo | B95: Research Data Associate | C95: Budapest, Budapest, Hungary | D95: Hybrid | E95: Full Time | F95: Syngenta Group | G95: Syngenta Group: Produces seeds and crop protection products for global agriculture. | H95: 3+ YOE3+ years in agricultural research data management or analytics; SQL, data visualization, GIS; experience in experimental design and statistical analysis; English proficiency. | I95: SQL, Power BI, Tableau, GIS software, Python, R, Drone imagery processing | J95: Job Posting | K95: 46083 | L95: Departments - Data and Analytics, Budapest (Remote, Hybrid, Onsite), No keyword search, 6 months | M95: =IFERROR(__xludf.DUMMYFUNCTION("TEXT( IF(RIGHT(A95,2)=""mo"", EDATE(DATEVALUE(K95), -VALUE(REGEXEXTRACT(A95,""\d+""))), DATEVALUE(K95) - IF(RIGHT(A95,1)=""h"", VALUE(REGEXEXTRACT(A95,""\d+""))/24, IF(RIGHT(A95,1)=""d"", VALUE(REGEXEXTRACT(A95,""\d+"")), IF(RI"&"GHT(A95,1)=""w"", VALUE(REGEXEXTRACT(A95,""\d+""))*7, 0))) ) , ""YYYY-M-D"")"),"2026-2-2") -> 2026-2-2
A96: 1mo | B96: Associate Managing Consultant, Advisors – Performance Analytics | C96: Budapest or Hungary | D96: Onsite | E96: Full Time | F96: Mastercard | G96: MastercardNYSE: MA: Facilitates global electronic payment transactions and financial technology services. | H96: Undergraduate degree with data analytics experience; client management; large data analysis; Python, R, SQL, SAS; advanced MS Office; English and local language; willingness to travel. | I96: Python, R, SQL, SAS, Hadoop, Impala, Hive, PySpark, Tableau, Power BI, Excel | J96: Job Posting | K96: 46083 | L96: Departments - Data and Analytics, Budapest (Remote, Hybrid, Onsite), No keyword search, 6 months | M96: =IFERROR(__xludf.DUMMYFUNCTION("TEXT( IF(RIGHT(A96,2)=""mo"", EDATE(DATEVALUE(K96), -VALUE(REGEXEXTRACT(A96,""\d+""))), DATEVALUE(K96) - IF(RIGHT(A96,1)=""h"", VALUE(REGEXEXTRACT(A96,""\d+""))/24, IF(RIGHT(A96,1)=""d"", VALUE(REGEXEXTRACT(A96,""\d+"")), IF(RI"&"GHT(A96,1)=""w"", VALUE(REGEXEXTRACT(A96,""\d+""))*7, 0))) ) , ""YYYY-M-D"")"),"2026-2-2") -> 2026-2-2
A97: 1mo | B97: Resource Planner | C97: Budapest, Budapest, Hungary | D97: Hybrid | E97: Full Time | F97: Marshmallow | G97: Marshmallow: Provides digital insurance and financial services for international migrants. | H97: Experience in Workforce Management/Resource Planning; strong analytics; advanced Google Sheets/Excel; Looker/BigQuery/SQL; experience with WFM systems (Assembled) and cross-functional collaboration. | I97: Google Sheets, Excel, Looker, BigQuery, SQL, Assembled WFM | J97: Job Posting | K97: 46083 | L97: Departments - Data and Analytics, Budapest (Remote, Hybrid, Onsite), No keyword search, 6 months | M97: =IFERROR(__xludf.DUMMYFUNCTION("TEXT( IF(RIGHT(A97,2)=""mo"", EDATE(DATEVALUE(K97), -VALUE(REGEXEXTRACT(A97,""\d+""))), DATEVALUE(K97) - IF(RIGHT(A97,1)=""h"", VALUE(REGEXEXTRACT(A97,""\d+""))/24, IF(RIGHT(A97,1)=""d"", VALUE(REGEXEXTRACT(A97,""\d+"")), IF(RI"&"GHT(A97,1)=""w"", VALUE(REGEXEXTRACT(A97,""\d+""))*7, 0))) ) , ""YYYY-M-D"")"),"2026-2-2") -> 2026-2-2
A98: 1mo | B98: Marketing Data Engineer | C98: United States or India or Europe | D98: Remote | E98: Full Time | F98: LHH | G98: LHHSIX Swiss Exchange: ADEN: Provides professional recruitment, coaching, and career transition services. | H98: 4+ YOE4+ years in data engineering for marketing or revenue operations; SQL; ETL/ELT frameworks; cloud data warehouses; data modeling; dashboards. | I98: SQL, Azure, dbt, Airflow, Fivetran, Stitch, GA4, Salesforce, Pardot/Marketing Cloud, Looker Studio, Power BI, Salesforce CRM, Google Ads, Marketing Automation | J98: Job Posting | K98: 46083 | L98: Departments - Data and Analytics, Budapest (Remote, Hybrid, Onsite), No keyword search, 6 months | M98: =IFERROR(__xludf.DUMMYFUNCTION("TEXT( IF(RIGHT(A98,2)=""mo"", EDATE(DATEVALUE(K98), -VALUE(REGEXEXTRACT(A98,""\d+""))), DATEVALUE(K98) - IF(RIGHT(A98,1)=""h"", VALUE(REGEXEXTRACT(A98,""\d+""))/24, IF(RIGHT(A98,1)=""d"", VALUE(REGEXEXTRACT(A98,""\d+"")), IF(RI"&"GHT(A98,1)=""w"", VALUE(REGEXEXTRACT(A98,""\d+""))*7, 0))) ) , ""YYYY-M-D"")"),"2026-2-2") -> 2026-2-2
A99: 1mo | B99: Reporting & Analytics Center of Excellence - Analyst | C99: Budapest, Budapest, Hungary | D99: Hybrid | E99: Full Time | F99: Albemarle | G99: AlbemarleNYSE: ALB: Manufactures specialty chemicals including lithium and bromine for global markets. | H99: 1+ YOEEnglish fluent; 1–3 years in reporting/analytics; experience with SAP S/4, SAP BW, Databricks, HANA Enterprise, SAP Analytics Cloud, SAP BO, Azure, PowerBI, Celonis or similar. | I99: SAP S/4, SAP BW, Databricks, HANA Enterprise, SAP Analytics Cloud, SAP Business Objects, Microsoft Azure, PowerBI, Celonis | J99: Job Posting | K99: 46083 | L99: Departments - Data and Analytics, Budapest (Remote, Hybrid, Onsite), No keyword search, 6 months | M99: =IFERROR(__xludf.DUMMYFUNCTION("TEXT( IF(RIGHT(A99,2)=""mo"", EDATE(DATEVALUE(K99), -VALUE(REGEXEXTRACT(A99,""\d+""))), DATEVALUE(K99) - IF(RIGHT(A99,1)=""h"", VALUE(REGEXEXTRACT(A99,""\d+""))/24, IF(RIGHT(A99,1)=""d"", VALUE(REGEXEXTRACT(A99,""\d+"")), IF(RI"&"GHT(A99,1)=""w"", VALUE(REGEXEXTRACT(A99,""\d+""))*7, 0))) ) , ""YYYY-M-D"")"),"2026-2-2") -> 2026-2-2
A100: 1mo | B100: Data Analyst Consultant - Industrial Projects (Energy sector) (Budapest, BU, HU, 1139) | C100: Budapest, Budapest, Hungary | D100: Hybrid | E100: Full Time | F100: Bilfinger | G100: BilfingerXETRA: GBF: Provides industrial services and engineering for the process industry. | H100: 4+ YOEBachelor's in Engineering, Data Science, Statistics or similar; 4+ years industrial analytics; Python/R/SQL; Power BI/Tableau/Grafana; PLC/SCADA/MES experience; strong statistical skills; good communication. | I100: Python, R, SQL, Power BI, Tableau, Grafana | J100: Job Posting | K100: 46083 | L100: Departments - Data and Analytics, Budapest (Remote, Hybrid, Onsite), No keyword search, 6 months | M100: =IFERROR(__xludf.DUMMYFUNCTION("TEXT( IF(RIGHT(A100,2)=""mo"", EDATE(DATEVALUE(K100), -VALUE(REGEXEXTRACT(A100,""\d+""))), DATEVALUE(K100) - IF(RIGHT(A100,1)=""h"", VALUE(REGEXEXTRACT(A100,""\d+""))/24, IF(RIGHT(A100,1)=""d"", VALUE(REGEXEXTRACT(A100,""\d+"")), "&" IF(RIGHT(A100,1)=""w"", VALUE(REGEXEXTRACT(A100,""\d+""))*7, 0))) ) , ""YYYY-M-D"")"),"2026-2-2") -> 2026-2-2
...

Sheet HiringCafe_Job_Clean
A1: Column column | B1: Data column | C1: Quality check
A5: Posted Time
A6: Role
A7: Area
A8: Work Type
A9: Contract Type
A10: Company
A11: Company & Description
A12: Requirements Summary
A13: Technical Tools mentioned
A14: Job Posting | C14: =IF(A14=B14, "Entry is True", "Check this Entry") -> Check this Entry

Sheet HiringCafe_Job_Format
A1: Posted Time | B1: Role | C1: Area | D1: Work Type | E1: Contract Type | F1: Company | G1: Company & Description | H1: Requirements Summary | I1: Technical Tools mentioned | J1: Job Posting | K1: Added Date | L1: Type of Search
A2: {=IFERROR(INDEX(HiringCafe_Job_Clean!$B:$B, SMALL(IF(HiringCafe_Job_Clean!$A$1:$A$5027="Posted Time", ROW(HiringCafe_Job_Clean!$A$1:$A$5027)), ROW()-1)), "")} | B2: {=IFERROR(INDEX(HiringCafe_Job_Clean!$B:$B, SMALL(IF(HiringCafe_Job_Clean!$A$1:$A$5027="Role", ROW(HiringCafe_Job_Clean!$A$1:$A$5027)), ROW()-1)), "")} | C2: {=IFERROR(INDEX(HiringCafe_Job_Clean!$B:$B, SMALL(IF(HiringCafe_Job_Clean!$A$1:$A$5027="Area", ROW(HiringCafe_Job_Clean!$A$1:$A$5027)), ROW()-1)), "")} | D2: {=IFERROR(INDEX(HiringCafe_Job_Clean!$B:$B, SMALL(IF(HiringCafe_Job_Clean!$A$1:$A$5027="Work Type", ROW(HiringCafe_Job_Clean!$A$1:$A$5027)), ROW()-1)), "")} | E2: {=IFERROR(INDEX(HiringCafe_Job_Clean!$B:$B, SMALL(IF(HiringCafe_Job_Clean!$A$1:$A$5027="Contract Type", ROW(HiringCafe_Job_Clean!$A$1:$A$5027)), ROW()-1)), "")} | F2: {=IFERROR(INDEX(HiringCafe_Job_Clean!$B:$B, SMALL(IF(HiringCafe_Job_Clean!$A$1:$A$5027="Company", ROW(HiringCafe_Job_Clean!$A$1:$A$5027)), ROW()-1)), "")} | G2: {=IFERROR(INDEX(HiringCafe_Job_Clean!$B:$B, SMALL(IF(HiringCafe_Job_Clean!$A$1:$A$5027="Company & Description", ROW(HiringCafe_Job_Clean!$A$1:$A$5027)), ROW()-1)), "")} | H2: {=IFERROR(INDEX(HiringCafe_Job_Clean!$B:$B, SMALL(IF(HiringCafe_Job_Clean!$A$1:$A$5027="Requirements Summary", ROW(HiringCafe_Job_Clean!$A$1:$A$5027)), ROW()-1)), "")} | I2: {=IFERROR(INDEX(HiringCafe_Job_Clean!$B:$B, SMALL(IF(HiringCafe_Job_Clean!$A$1:$A$5027="Technical Tools mentioned", ROW(HiringCafe_Job_Clean!$A$1:$A$5027)), ROW()-1)), "")} | J2: {=IFERROR(INDEX(HiringCafe_Job_Clean!$B:$B, SMALL(IF(HiringCafe_Job_Clean!$A$1:$A$5027="Job Posting", ROW(HiringCafe_Job_Clean!$A$1:$A$5027)), ROW()-1)), "")}
K201: - | L201: -
